{
  "materialsData": [
    {
      "number": 1,
      "name": "man_pk_scarf_a.mat"
    }
  ],
  "variations": [
    {
      "id": "1",
      "materialsData": [
        {
          "number": 1,
          "name": "man_pk_scarf_a.mat"
        }
      ],
      "materialsResources": [
        {
          "number": 1,
          "resources": [
            {
              "name": "man_pk_scarf_a_pattern.mat",
              "selected": true,
              "layoutId": 4,
              "loadFlags": "S",
              "rttiValues": [
                {
                  "name": "dif_0_val",
                  "type": 4,
                  "val_str": null
                }
              ]
            }
          ]
        }
      ]
    },
    {
      "id": "2",
      "materialsData": [
        {
          "number": 1,
          "name": "man_pk_scarf_a.mat"
        }
      ],
      "materialsResources": [
        {
          "number": 1,
          "resources": [
            {
              "name": "man_pk_scarf_a.mat",
              "selected": true,
              "layoutId": 4,
              "loadFlags": "S",
              "rttiValues": [
                {
                  "name": "dif_0_tex",
                  "type": 7,
                  "val_str": "chr_dark_khaki_dif.png"
                }
              ]
            }
          ]
        }
      ]
    },
    {
      "id": "3",
      "materialsData": [
        {
          "number": 1,
          "name": "man_pk_scarf_a.mat"
        }
      ],
      "materialsResources": [
        {
          "number": 1,
          "resources": [
            {
              "name": "man_pk_scarf_a_pattern.mat",
              "selected": true,
              "layoutId": 4,
              "loadFlags": "S",
              "rttiValues": [
                {
                  "name": "det_0_a_scale_factor",
                  "type": 2,
                  "val_str": null
                },
                {
                  "name": "det_0_clr_a_tex",
                  "type": 7,
                  "val_str": "srf_wool_c_dtt.png"
                },
                {
                  "name": "dif_0_tex",
                  "type": 7,
                  "val_str": "chr_white_dif.png"
                },
                {
                  "name": "dif_0_val",
                  "type": 4,
                  "val_str": null
                }
              ]
            }
          ]
        }
      ]
    }
  ]
}