{
  "materialsData": [
    {
      "number": 1,
      "name": "man_bdt_arms_armor_j.mat"
    }
  ],
  "variations": [
    {
      "id": "1",
      "materialsData": [
        {
          "number": 1,
          "name": "man_bdt_arms_armor_j.mat"
        }
      ],
      "materialsResources": [
        {
          "number": 1,
          "resources": [
            {
              "name": "man_bdt_arms_armor_j_gold.mat",
              "selected": true,
              "layoutId": 4,
              "loadFlags": "S",
              "rttiValues": []
            }
          ]
        }
      ]
    }
  ]
}