{
    "materialsData": [
        {
            "number": 1,
            "name": "chr_decal_logo_city.mat"
        }
    ],
    "variations": [
        {
            "id": "1",
            "materials": [
                {
                    "number": 1,
                    "name": "chr_decal_logo_vintage.mat"
                }
            ]
        },
        {
            "id": "2",
            "materials": [
                {
                    "number": 1,
                    "name": "chr_decal_logo_sun.mat"
                }
            ]
        },
        {
            "id": "3",
            "materials": [
                {
                    "number": 1,
                    "name": "chr_decal_logo_sign_i.mat"
                }
            ]
        },
        {
            "id": "4",
            "materials": [
                {
                    "number": 1,
                    "name": "chr_decal_logo_city.mat"
                }
            ]
        }
    ]
}