{
  "materialsData": [
    {
      "number": 1,
      "name": "man_bdt_gloves_d.mat"
    },
    {
      "number": 2,
      "name": "wmn_hands_white_a.mat"
    }
  ],
  "variations": [
    {
      "id": "1",
      "materialsData": [
        {
          "number": 1,
          "name": "man_bdt_gloves_d.mat"
        },
        {
          "number": 2,
          "name": "wmn_hands_white_a.mat"
        }
      ],
      "materialsResources": [
        {
          "number": 1,
          "resources": [
            {
              "name": "man_bdt_gloves_d.mat",
              "selected": true,
              "layoutId": 4,
              "loadFlags": "S",
              "rttiValues": []
            }
          ]
        },
        {
          "number": 2,
          "resources": [
            {
              "name": "wmn_hands_black_a.mat",
              "selected": true,
              "layoutId": 4,
              "loadFlags": "S",
              "rttiValues": []
            }
          ]
        }
      ]
    }
  ]
}