{
    "materialsData": [
        {
            "number": 1,
            "name": "npc_hair_a.mat"
        }
    ],
    "variations": {
        "1": [
            {
                "number": 1,
                "name": "npc_hair_a_grey.mat"
            }
        ],
        "2": [
            {
                "number": 1,
                "name": "npc_hair_a.mat"
            }
        ],
        "3": [
            {
                "number": 1,
                "name": "npc_hair_a_dark.mat"
            }
        ],
        "4": [
            {
                "number": 1,
                "name": "npc_hair_a_grey.mat"
            }
        ],
        "5": [
            {
                "number": 1,
                "name": "npc_hair_a_dark.mat"
            }
        ],
        "6": [
            {
                "number": 1,
                "name": "npc_hair_a.mat"
            }
        ],
        "7": [
            {
                "number": 1,
                "name": "npc_hair_a_dark.mat"
            }
        ],
        "8": [
            {
                "number": 1,
                "name": "npc_hair_a.mat"
            }
        ],
        "9": [
            {
                "number": 1,
                "name": "npc_hair_a_dark.mat"
            }
        ],
        "10": [
            {
                "number": 1,
                "name": "npc_hair_a.mat"
            }
        ],
        "11": [
            {
                "number": 1,
                "name": "npc_hair_a_dark.mat"
            }
        ],
        "12": [
            {
                "number": 1,
                "name": "zmb_banshee_hairs_a.mat"
            }
        ],
        "13": [
            {
                "number": 1,
                "name": "viral_hair_a.mat"
            }
        ],
        "14": [
            {
                "number": 1,
                "name": "zmb_banshee_hairs_a.mat"
            }
        ],
        "15": [
            {
                "number": 1,
                "name": "viral_hair_a.mat"
            }
        ],
        "16": [
            {
                "number": 1,
                "name": "npc_hair_a_dark.mat"
            }
        ],
        "17": [
            {
                "number": 1,
                "name": "zmb_banshee_hairs_a.mat"
            }
        ]
    }
}