{
    "materialsData": [
        {
            "number": 1,
            "name": "sh_scan_man_021.mat"
        },
        {
            "number": 2,
            "name": "sh_eye.mat"
        },
        {
            "number": 3,
            "name": "sh_mouth_interior.mat"
        },
        {
            "number": 4,
            "name": "sh_eyelashes.mat"
        },
        {
            "number": 5,
            "name": "sh_eye_shadow.mat"
        },
        {
            "number": 6,
            "name": "sh_wet_eye.mat"
        }
    ],
    "variations": {
        "1": [
            {
                "number": 1,
                "name": "sh_man_pk_e.mat"
            },
            {
                "number": 2,
                "name": "sh_eye_green.mat"
            },
            {
                "number": 3,
                "name": "sh_mouth_interior.mat"
            },
            {
                "number": 4,
                "name": "sh_eyelashes.mat"
            },
            {
                "number": 5,
                "name": "sh_eye_shadow.mat"
            },
            {
                "number": 6,
                "name": "sh_wet_eye.mat"
            }
        ],
        "2": [
            {
                "number": 1,
                "name": "sh_scan_man_041.mat"
            },
            {
                "number": 2,
                "name": "sh_eye_green.mat"
            },
            {
                "number": 3,
                "name": "sh_mouth_interior.mat"
            },
            {
                "number": 4,
                "name": "sh_eyelashes.mat"
            },
            {
                "number": 5,
                "name": "sh_eye_shadow.mat"
            },
            {
                "number": 6,
                "name": "sh_wet_eye.mat"
            }
        ],
        "3": [
            {
                "number": 1,
                "name": "sh_scan_man_003.mat"
            },
            {
                "number": 2,
                "name": "sh_eye_green.mat"
            },
            {
                "number": 3,
                "name": "sh_mouth_interior.mat"
            },
            {
                "number": 4,
                "name": "sh_eyelashes.mat"
            },
            {
                "number": 5,
                "name": "sh_eye_shadow.mat"
            },
            {
                "number": 6,
                "name": "sh_wet_eye.mat"
            }
        ],
        "4": [
            {
                "number": 1,
                "name": "sh_scan_man_030.mat"
            },
            {
                "number": 2,
                "name": "sh_eye_blue.mat"
            },
            {
                "number": 3,
                "name": "sh_mouth_interior.mat"
            },
            {
                "number": 4,
                "name": "sh_eyelashes.mat"
            },
            {
                "number": 5,
                "name": "sh_eye_shadow.mat"
            },
            {
                "number": 6,
                "name": "sh_wet_eye.mat"
            }
        ],
        "5": [
            {
                "number": 1,
                "name": "sh_scan_man_055.mat"
            },
            {
                "number": 2,
                "name": "sh_eye_grey.mat"
            },
            {
                "number": 3,
                "name": "sh_mouth_interior.mat"
            },
            {
                "number": 4,
                "name": "sh_eyelashes.mat"
            },
            {
                "number": 5,
                "name": "sh_eye_shadow.mat"
            },
            {
                "number": 6,
                "name": "sh_wet_eye.mat"
            }
        ],
        "6": [
            {
                "number": 1,
                "name": "sh_man_pk_e.mat"
            },
            {
                "number": 2,
                "name": "sh_eye_green.mat"
            },
            {
                "number": 3,
                "name": "sh_mouth_interior.mat"
            },
            {
                "number": 4,
                "name": "sh_eyelashes.mat"
            },
            {
                "number": 5,
                "name": "sh_eye_shadow.mat"
            },
            {
                "number": 6,
                "name": "sh_wet_eye.mat"
            }
        ],
        "7": [
            {
                "number": 1,
                "name": "sh_scan_man_021.mat"
            },
            {
                "number": 2,
                "name": "sh_eye.mat"
            },
            {
                "number": 3,
                "name": "sh_mouth_interior.mat"
            },
            {
                "number": 4,
                "name": "sh_eyelashes.mat"
            },
            {
                "number": 5,
                "name": "sh_eye_shadow.mat"
            },
            {
                "number": 6,
                "name": "sh_wet_eye.mat"
            }
        ],
        "8": [
            {
                "number": 1,
                "name": "sh_scan_man_041.mat"
            },
            {
                "number": 2,
                "name": "sh_eye_green.mat"
            },
            {
                "number": 3,
                "name": "sh_mouth_interior.mat"
            },
            {
                "number": 4,
                "name": "sh_eyelashes.mat"
            },
            {
                "number": 5,
                "name": "sh_eye_shadow.mat"
            },
            {
                "number": 6,
                "name": "sh_wet_eye.mat"
            }
        ],
        "9": [
            {
                "number": 1,
                "name": "sh_scan_man_030.mat"
            },
            {
                "number": 2,
                "name": "sh_eye_blue.mat"
            },
            {
                "number": 3,
                "name": "sh_mouth_interior.mat"
            },
            {
                "number": 4,
                "name": "sh_eyelashes.mat"
            },
            {
                "number": 5,
                "name": "sh_eye_shadow.mat"
            },
            {
                "number": 6,
                "name": "sh_wet_eye.mat"
            }
        ],
        "10": [
            {
                "number": 1,
                "name": "sh_scan_man_041.mat"
            },
            {
                "number": 2,
                "name": "sh_eye_green.mat"
            },
            {
                "number": 3,
                "name": "sh_mouth_interior.mat"
            },
            {
                "number": 4,
                "name": "sh_eyelashes.mat"
            },
            {
                "number": 5,
                "name": "sh_eye_shadow.mat"
            },
            {
                "number": 6,
                "name": "sh_wet_eye.mat"
            }
        ],
        "11": [
            {
                "number": 1,
                "name": "sh_man_bdt_a.mat"
            },
            {
                "number": 2,
                "name": "sh_eye_green.mat"
            },
            {
                "number": 3,
                "name": "sh_mouth_interior.mat"
            },
            {
                "number": 4,
                "name": "sh_eyelashes.mat"
            },
            {
                "number": 5,
                "name": "sh_eye_shadow.mat"
            },
            {
                "number": 6,
                "name": "sh_wet_eye.mat"
            }
        ],
        "12": [
            {
                "number": 1,
                "name": "sh_biter_b.mat"
            },
            {
                "number": 2,
                "name": "sh_eye_degenerated.mat"
            },
            {
                "number": 3,
                "name": "sh_mouth_interior_zmb.mat"
            },
            {
                "number": 4,
                "name": "sh_eyelashes.mat"
            },
            {
                "number": 5,
                "name": "sh_eye_shadow.mat"
            },
            {
                "number": 6,
                "name": "sh_wet_eye.mat"
            }
        ],
        "13": [
            {
                "number": 1,
                "name": "sh_biter_a.mat"
            },
            {
                "number": 2,
                "name": "sh_eye_degenerated.mat"
            },
            {
                "number": 3,
                "name": "sh_mouth_interior_zmb.mat"
            },
            {
                "number": 4,
                "name": "sh_eyelashes.mat"
            },
            {
                "number": 5,
                "name": "sh_eye_shadow.mat"
            },
            {
                "number": 6,
                "name": "sh_wet_eye.mat"
            }
        ],
        "14": [
            {
                "number": 1,
                "name": "sh_biter_b.mat"
            },
            {
                "number": 2,
                "name": "sh_eye_degenerated.mat"
            },
            {
                "number": 3,
                "name": "sh_mouth_interior_zmb.mat"
            },
            {
                "number": 4,
                "name": "sh_eyelashes.mat"
            },
            {
                "number": 5,
                "name": "sh_eye_shadow.mat"
            },
            {
                "number": 6,
                "name": "sh_wet_eye.mat"
            }
        ],
        "15": [
            {
                "number": 1,
                "name": "sh_biter_deg_b.mat"
            },
            {
                "number": 2,
                "name": "sh_eye_degenerated.mat"
            },
            {
                "number": 3,
                "name": "sh_mouth_interior_zmb.mat"
            },
            {
                "number": 4,
                "name": "sh_eyelashes.mat"
            },
            {
                "number": 5,
                "name": "sh_eye_shadow.mat"
            },
            {
                "number": 6,
                "name": "sh_wet_eye.mat"
            }
        ],
        "16": [
            {
                "number": 1,
                "name": "sh_man_wrestler_w_paint_c.mat"
            },
            {
                "number": 2,
                "name": "sh_eye.mat"
            },
            {
                "number": 3,
                "name": "sh_mouth_interior.mat"
            },
            {
                "number": 4,
                "name": "sh_eyelashes.mat"
            },
            {
                "number": 5,
                "name": "sh_eye_shadow.mat"
            },
            {
                "number": 6,
                "name": "sh_wet_eye.mat"
            }
        ],
        "17": [
            {
                "number": 1,
                "name": "sh_scan_man_008.mat"
            },
            {
                "number": 2,
                "name": "sh_eye.mat"
            },
            {
                "number": 3,
                "name": "sh_mouth_interior.mat"
            },
            {
                "number": 4,
                "name": "sh_eyelashes.mat"
            },
            {
                "number": 5,
                "name": "sh_eye_shadow.mat"
            },
            {
                "number": 6,
                "name": "sh_wet_eye.mat"
            }
        ]
    },
    "bones": [
        {
            "boneName": "scan_man_021_lod_0",
            "position": [
                "0.000000",
                "0.000000",
                "0.000000"
            ],
            "rotation": [
                "0",
                "0",
                "0",
                "1"
            ]
        },
        {
            "boneName": "spine3",
            "position": [
                "-0.000003",
                "1.273712",
                "-0.037899"
            ],
            "rotation": [
                "0.707107",
                "0.707107",
                "0.000004",
                "0.000001"
            ]
        },
        {
            "boneName": "l_clavicle",
            "position": [
                "0.046151",
                "1.391114",
                "0.011084"
            ],
            "rotation": [
                "0.973939",
                "0.115295",
                "-0.190701",
                "-0.042225"
            ]
        },
        {
            "boneName": "r_clavicle",
            "position": [
                "-0.046159",
                "1.391115",
                "0.011083"
            ],
            "rotation": [
                "0.115295",
                "0.973938",
                "0.042226",
                "0.190709"
            ]
        },
        {
            "boneName": "neck",
            "position": [
                "-0.000004",
                "1.465118",
                "-0.029828"
            ],
            "rotation": [
                "0.699432",
                "0.699427",
                "0.103916",
                "-0.10391"
            ]
        },
        {
            "boneName": "neck1",
            "position": [
                "-0.000003",
                "1.540256",
                "-0.006998"
            ],
            "rotation": [
                "0.706083",
                "0.706077",
                "0.038101",
                "-0.038096"
            ]
        },
        {
            "boneName": "head",
            "position": [
                "-0.000003",
                "1.619920",
                "0.001624"
            ],
            "rotation": [
                "0.707107",
                "0.707107",
                "0.000004",
                "0.000001"
            ]
        },
        {
            "boneName": "l_down_front_lipsin_bone",
            "position": [
                "0.004629",
                "1.595243",
                "0.127411"
            ],
            "rotation": [
                "0.765937",
                "0.079687",
                "0.627373",
                "0.115727"
            ]
        },
        {
            "boneName": "r_center_nasolabialcrease_bone",
            "position": [
                "-0.038742",
                "1.607357",
                "0.114256"
            ],
            "rotation": [
                "0.427129",
                "-0.034045",
                "0.901388",
                "-0.062463"
            ]
        },
        {
            "boneName": "l_center_nasolabialcrease_bone",
            "position": [
                "0.034911",
                "1.606616",
                "0.112729"
            ],
            "rotation": [
                "0.912059",
                "-0.068578",
                "0.404036",
                "-0.014131"
            ]
        },
        {
            "boneName": "l_up_front_lipsin_bone",
            "position": [
                "0.004360",
                "1.601813",
                "0.129505"
            ],
            "rotation": [
                "0.738013",
                "-0.327376",
                "0.529236",
                "-0.260904"
            ]
        },
        {
            "boneName": "l_down_front_lipsout_bone",
            "position": [
                "0.015052",
                "1.596504",
                "0.122007"
            ],
            "rotation": [
                "0.830092",
                "-0.069561",
                "0.431297",
                "0.346542"
            ]
        },
        {
            "boneName": "l_nosecorner_bone",
            "position": [
                "0.018906",
                "1.628815",
                "0.120148"
            ],
            "rotation": [
                "0.85351",
                "0.05949",
                "0.514492",
                "-0.057268"
            ]
        },
        {
            "boneName": "r_down_front_lipsin_bone",
            "position": [
                "-0.007060",
                "1.595679",
                "0.127763"
            ],
            "rotation": [
                "0.656712",
                "0.124279",
                "0.737534",
                "0.096576"
            ]
        },
        {
            "boneName": "r_out_mouthcorner_bone",
            "position": [
                "-0.025084",
                "1.597859",
                "0.115977"
            ],
            "rotation": [
                "0.463032",
                "0.536722",
                "0.705202",
                "-0.014883"
            ]
        },
        {
            "boneName": "l_mandible_bone",
            "position": [
                "0.028940",
                "1.568884",
                "0.098297"
            ],
            "rotation": [
                "0.920702",
                "-0.304351",
                "0.237524",
                "-0.057097"
            ]
        },
        {
            "boneName": "l_out_mouthcorner_bone",
            "position": [
                "0.022135",
                "1.596862",
                "0.115092"
            ],
            "rotation": [
                "-0.745883",
                "0.128493",
                "-0.437735",
                "-0.48532"
            ]
        },
        {
            "boneName": "r_zygoma_bone",
            "position": [
                "-0.048783",
                "1.634847",
                "0.109011"
            ],
            "rotation": [
                "0.440047",
                "-0.001251",
                "0.897971",
                "-0.002173"
            ]
        },
        {
            "boneName": "l_centercheek_bone",
            "position": [
                "0.050911",
                "1.605055",
                "0.093949"
            ],
            "rotation": [
                "0.950835",
                "-0.096193",
                "0.292344",
                "-0.034565"
            ]
        },
        {
            "boneName": "r_up_front_lipsin_bone",
            "position": [
                "-0.007066",
                "1.601969",
                "0.129962"
            ],
            "rotation": [
                "0.542207",
                "-0.285248",
                "0.71411",
                "-0.338662"
            ]
        },
        {
            "boneName": "r_up_front_lipsout_bone",
            "position": [
                "-0.017051",
                "1.601445",
                "0.125943"
            ],
            "rotation": [
                "0.49241",
                "-0.264833",
                "0.73462",
                "-0.384356"
            ]
        },
        {
            "boneName": "r_in_browup_bone",
            "position": [
                "-0.031912",
                "1.700663",
                "0.122678"
            ],
            "rotation": [
                "-0.522989",
                "-0.120363",
                "-0.827081",
                "-0.167131"
            ]
        },
        {
            "boneName": "l_up_front_lipsout_bone",
            "position": [
                "0.013992",
                "1.601453",
                "0.124700"
            ],
            "rotation": [
                "0.761623",
                "-0.372304",
                "0.465334",
                "-0.254527"
            ]
        },
        {
            "boneName": "c_centerchin_bone",
            "position": [
                "-0.002273",
                "1.568529",
                "0.120954"
            ],
            "rotation": [
                "0.703288",
                "-0.098094",
                "0.698413",
                "-0.089355"
            ]
        },
        {
            "boneName": "l_mouthcorner_bone",
            "position": [
                "0.021820",
                "1.600199",
                "0.116761"
            ],
            "rotation": [
                "0.665749",
                "-0.496159",
                "0.448816",
                "-0.330406"
            ]
        },
        {
            "boneName": "r_nosecorner_bone",
            "position": [
                "-0.022835",
                "1.629883",
                "0.121693"
            ],
            "rotation": [
                "-0.51146",
                "0.082457",
                "-0.851946",
                "-0.076145"
            ]
        },
        {
            "boneName": "l_zygoma_bone",
            "position": [
                "0.044794",
                "1.633668",
                "0.108254"
            ],
            "rotation": [
                "0.896829",
                "-0.030937",
                "0.441198",
                "0.009244"
            ]
        },
        {
            "boneName": "l_up_nasolabialcrease_bone",
            "position": [
                "0.026466",
                "1.619267",
                "0.117924"
            ],
            "rotation": [
                "0.811313",
                "0.078423",
                "0.576479",
                "-0.057379"
            ]
        },
        {
            "boneName": "l_in_browup_bone",
            "position": [
                "0.028522",
                "1.699117",
                "0.121761"
            ],
            "rotation": [
                "0.831044",
                "0.165891",
                "0.514357",
                "0.131464"
            ]
        },
        {
            "boneName": "r_mandible_bone",
            "position": [
                "-0.034318",
                "1.569569",
                "0.099881"
            ],
            "rotation": [
                "0.24672",
                "-0.075802",
                "0.914484",
                "-0.311612"
            ]
        },
        {
            "boneName": "r_in_browdown_bone",
            "position": [
                "-0.020798",
                "1.679770",
                "0.121762"
            ],
            "rotation": [
                "0.426275",
                "-0.227922",
                "0.792393",
                "-0.372095"
            ]
        },
        {
            "boneName": "l_in_browdown_bone",
            "position": [
                "0.017075",
                "1.678516",
                "0.122419"
            ],
            "rotation": [
                "0.778963",
                "-0.385068",
                "0.451371",
                "-0.202989"
            ]
        },
        {
            "boneName": "r_centercheek_bone",
            "position": [
                "-0.056430",
                "1.605871",
                "0.096011"
            ],
            "rotation": [
                "0.301729",
                "-0.029993",
                "0.949393",
                "-0.081932"
            ]
        },
        {
            "boneName": "r_mouthcorner_bone",
            "position": [
                "-0.024390",
                "1.600446",
                "0.117539"
            ],
            "rotation": [
                "0.395133",
                "-0.322878",
                "0.710253",
                "-0.484933"
            ]
        },
        {
            "boneName": "r_down_front_lipsout_bone",
            "position": [
                "-0.017736",
                "1.597369",
                "0.123033"
            ],
            "rotation": [
                "0.454429",
                "0.339988",
                "0.822523",
                "-0.036853"
            ]
        },
        {
            "boneName": "r_up_nasolabialcrease_bone",
            "position": [
                "-0.030149",
                "1.620144",
                "0.119374"
            ],
            "rotation": [
                "-0.563608",
                "0.057958",
                "-0.820006",
                "-0.081095"
            ]
        },
        {
            "boneName": "r_cen_eyelidupaimbase_bone",
            "position": [
                "-0.033060",
                "1.672472",
                "0.103950"
            ],
            "rotation": [
                "-0.384444",
                "0.481263",
                "-0.593467",
                "-0.51806"
            ]
        },
        {
            "boneName": "l_angulioris_bone",
            "position": [
                "0.030691",
                "1.584492",
                "0.106748"
            ],
            "rotation": [
                "0.891463",
                "-0.203167",
                "0.403525",
                "0.034421"
            ]
        },
        {
            "boneName": "l_upcheek_bone",
            "position": [
                "0.012864",
                "1.561621",
                "0.112048"
            ],
            "rotation": [
                "0.837848",
                "-0.36298",
                "0.390095",
                "-0.118672"
            ]
        },
        {
            "boneName": "r_infraorbitalfurrow_bone",
            "position": [
                "-0.058124",
                "1.630744",
                "0.099095"
            ],
            "rotation": [
                "0.311883",
                "-0.003539",
                "0.948484",
                "-0.055629"
            ]
        },
        {
            "boneName": "l_in_eyelidupaimbase_bone",
            "position": [
                "0.029522",
                "1.670949",
                "0.103684"
            ],
            "rotation": [
                "-0.246394",
                "0.63996",
                "-0.662789",
                "-0.300751"
            ]
        },
        {
            "boneName": "l_headaddside2a_bone",
            "position": [
                "0.061859",
                "1.697053",
                "0.079689"
            ],
            "rotation": [
                "0.983003",
                "0.042105",
                "0.175984",
                "0.031003"
            ]
        },
        {
            "boneName": "r_out_eyeliddownaimbase_bone",
            "position": [
                "-0.033060",
                "1.672472",
                "0.103950"
            ],
            "rotation": [
                "0.324132",
                "-0.698009",
                "0.628441",
                "0.113064"
            ]
        },
        {
            "boneName": "c_up_lipscenter_bone",
            "position": [
                "-0.001743",
                "1.600293",
                "0.125556"
            ],
            "rotation": [
                "0.468544",
                "-0.542593",
                "0.483714",
                "-0.502076"
            ]
        },
        {
            "boneName": "l_in_mouthdown_bone",
            "position": [
                "0.011472",
                "1.588512",
                "0.121988"
            ],
            "rotation": [
                "0.841212",
                "-0.31629",
                "0.437938",
                "-0.023105"
            ]
        },
        {
            "boneName": "l_headaddside1e_bone",
            "position": [
                "0.060452",
                "1.720353",
                "-0.034210"
            ],
            "rotation": [
                "0.949048",
                "0.135185",
                "-0.279616",
                "0.053362"
            ]
        },
        {
            "boneName": "r_headaddside3c_bone",
            "position": [
                "-0.075629",
                "1.698034",
                "-0.012680"
            ],
            "rotation": [
                "0.120715",
                "-0.048065",
                "-0.991203",
                "-0.025169"
            ]
        },
        {
            "boneName": "r_headaddside1f_bone",
            "position": [
                "-0.055642",
                "1.665601",
                "-0.045320"
            ],
            "rotation": [
                "-0.350337",
                "0.098433",
                "0.930029",
                "-0.051194"
            ]
        },
        {
            "boneName": "l_down_mouthcorner_bone",
            "position": [
                "0.021115",
                "1.599251",
                "0.113522"
            ],
            "rotation": [
                "0.427544",
                "0.415618",
                "0.473117",
                "0.648559"
            ]
        },
        {
            "boneName": "c_submental_bone",
            "position": [
                "-0.002920",
                "1.556931",
                "0.104189"
            ],
            "rotation": [
                "0.553317",
                "-0.48048",
                "0.523921",
                "-0.43415"
            ]
        },
        {
            "boneName": "l_nose_nasolabial_bone",
            "position": [
                "0.021218",
                "1.643139",
                "0.117800"
            ],
            "rotation": [
                "0.810843",
                "0.175582",
                "0.5583",
                "0.00226"
            ]
        },
        {
            "boneName": "c_headaddg_bone",
            "position": [
                "-0.002060",
                "1.617399",
                "-0.048294"
            ],
            "rotation": [
                "0.714718",
                "-0.134633",
                "-0.681427",
                "0.081915"
            ]
        },
        {
            "boneName": "c_endnose_bone",
            "position": [
                "-0.001237",
                "1.630197",
                "0.148923"
            ],
            "rotation": [
                "-0.692264",
                "-0.010078",
                "-0.718887",
                "-0.062222"
            ]
        },
        {
            "boneName": "l_headaddside1g_bone",
            "position": [
                "0.047746",
                "1.619780",
                "-0.022249"
            ],
            "rotation": [
                "0.930424",
                "-0.116657",
                "-0.334677",
                "0.093237"
            ]
        },
        {
            "boneName": "r_headaddbangs_bone",
            "position": [
                "-0.050512",
                "1.691427",
                "0.109763"
            ],
            "rotation": [
                "-0.329044",
                "-0.018176",
                "-0.941453",
                "-0.071169"
            ]
        },
        {
            "boneName": "r_eyeup_wrinkle_bone",
            "position": [
                "-0.035011",
                "1.680510",
                "0.117922"
            ],
            "rotation": [
                "0.636297",
                "-0.155373",
                "0.732339",
                "-0.186188"
            ]
        },
        {
            "boneName": "r_center_eyebrow_bone",
            "position": [
                "-0.039980",
                "1.687573",
                "0.118821"
            ],
            "rotation": [
                "0.480522",
                "-0.059004",
                "0.864771",
                "-0.133371"
            ]
        },
        {
            "boneName": "r_up_nasolabial_bone",
            "position": [
                "-0.033483",
                "1.629229",
                "0.118450"
            ],
            "rotation": [
                "-0.599692",
                "0.017144",
                "-0.799737",
                "-0.022306"
            ]
        },
        {
            "boneName": "l_headaddside3d_bone",
            "position": [
                "0.068006",
                "1.650021",
                "-0.010163"
            ],
            "rotation": [
                "0.973659",
                "-0.114465",
                "-0.172246",
                "0.096004"
            ]
        },
        {
            "boneName": "l_tongue3_bone",
            "position": [
                "0.013961",
                "1.595155",
                "0.096455"
            ],
            "rotation": [
                "0.74656",
                "-0.244732",
                "-0.090069",
                "0.612081"
            ]
        },
        {
            "boneName": "r_down_nasolabial_bone",
            "position": [
                "-0.049121",
                "1.582318",
                "0.092395"
            ],
            "rotation": [
                "0.246575",
                "-0.070328",
                "0.937805",
                "-0.234045"
            ]
        },
        {
            "boneName": "l_tongue2_bone",
            "position": [
                "0.018481",
                "1.600645",
                "0.071222"
            ],
            "rotation": [
                "-0.671672",
                "-0.011473",
                "-0.050006",
                "-0.73907"
            ]
        },
        {
            "boneName": "l_eyeup_wrinkle_bone",
            "position": [
                "0.030685",
                "1.678623",
                "0.118632"
            ],
            "rotation": [
                "0.718605",
                "-0.230225",
                "0.638875",
                "-0.149806"
            ]
        },
        {
            "boneName": "r_in_eyeliddownaimbase_bone",
            "position": [
                "-0.033060",
                "1.672472",
                "0.103950"
            ],
            "rotation": [
                "0.678565",
                "-0.4219",
                "0.198872",
                "0.567451"
            ]
        },
        {
            "boneName": "c_centerchinup_bone",
            "position": [
                "-0.002148",
                "1.585805",
                "0.122351"
            ],
            "rotation": [
                "0.700885",
                "-0.152475",
                "0.686717",
                "-0.118032"
            ]
        },
        {
            "boneName": "r_in_eyebrow_bone",
            "position": [
                "-0.020540",
                "1.685175",
                "0.127810"
            ],
            "rotation": [
                "0.56068",
                "-0.14489",
                "0.792401",
                "-0.191692"
            ]
        },
        {
            "boneName": "r_out_infraorbital_bone",
            "position": [
                "-0.051264",
                "1.664507",
                "0.103220"
            ],
            "rotation": [
                "-0.329738",
                "-0.05191",
                "-0.937606",
                "-0.097328"
            ]
        },
        {
            "boneName": "l_headaddzygoma_bone",
            "position": [
                "0.052881",
                "1.646404",
                "0.102319"
            ],
            "rotation": [
                "0.925855",
                "0.003919",
                "0.37755",
                "0.015288"
            ]
        },
        {
            "boneName": "r_in_infraorbital_bone",
            "position": [
                "-0.027311",
                "1.663531",
                "0.114473"
            ],
            "rotation": [
                "0.802067",
                "-0.083276",
                "0.588782",
                "-0.055584"
            ]
        },
        {
            "boneName": "l_down_lipsout_bone",
            "position": [
                "0.015632",
                "1.599865",
                "0.117874"
            ],
            "rotation": [
                "0.541652",
                "0.598728",
                "0.39088",
                "0.441984"
            ]
        },
        {
            "boneName": "r_eyeout_wrinkle_bone",
            "position": [
                "-0.050188",
                "1.674223",
                "0.105123"
            ],
            "rotation": [
                "0.436555",
                "-0.094295",
                "0.870058",
                "-0.208629"
            ]
        },
        {
            "boneName": "l_eyeballaimbase_bone",
            "position": [
                "0.029522",
                "1.670949",
                "0.103684"
            ],
            "rotation": [
                "0.523417",
                "-0.493414",
                "0.475431",
                "0.5065"
            ]
        },
        {
            "boneName": "r_in_mouthdown_bone",
            "position": [
                "-0.014906",
                "1.589003",
                "0.122805"
            ],
            "rotation": [
                "0.455966",
                "-0.039434",
                "0.826209",
                "-0.32851"
            ]
        },
        {
            "boneName": "c_tongue1_bone",
            "position": [
                "-0.001917",
                "1.593876",
                "0.049617"
            ],
            "rotation": [
                "-0.493817",
                "0.506107",
                "0.493817",
                "-0.506107"
            ]
        },
        {
            "boneName": "r_tongue2_bone",
            "position": [
                "-0.022315",
                "1.600647",
                "0.071221"
            ],
            "rotation": [
                "0.050006",
                "0.73907",
                "0.671672",
                "0.011473"
            ]
        },
        {
            "boneName": "r_eyeballaimbase_bone",
            "position": [
                "-0.033060",
                "1.672472",
                "0.103950"
            ],
            "rotation": [
                "0.493235",
                "-0.518302",
                "0.506675",
                "0.481002"
            ]
        },
        {
            "boneName": "r_nostril_bone",
            "position": [
                "-0.017652",
                "1.631719",
                "0.130050"
            ],
            "rotation": [
                "-0.263678",
                "0.222546",
                "-0.935344",
                "-0.077969"
            ]
        },
        {
            "boneName": "l_down_lipsin_bone",
            "position": [
                "0.007918",
                "1.600766",
                "0.121856"
            ],
            "rotation": [
                "0.539502",
                "0.523631",
                "0.413165",
                "0.513851"
            ]
        },
        {
            "boneName": "r_cen_eyeliddownaimbase_bone",
            "position": [
                "-0.033060",
                "1.672472",
                "0.103950"
            ],
            "rotation": [
                "0.545288",
                "-0.642931",
                "0.450179",
                "0.294345"
            ]
        },
        {
            "boneName": "r_tongue3_bone",
            "position": [
                "-0.017797",
                "1.595156",
                "0.096455"
            ],
            "rotation": [
                "-0.090069",
                "0.612081",
                "0.74656",
                "-0.244732"
            ]
        },
        {
            "boneName": "l_out_forehead_bone",
            "position": [
                "0.050434",
                "1.701849",
                "0.100352"
            ],
            "rotation": [
                "0.9552",
                "0.070223",
                "0.287016",
                "0.016833"
            ]
        },
        {
            "boneName": "l_out_mouthup_bone",
            "position": [
                "0.025527",
                "1.606167",
                "0.119934"
            ],
            "rotation": [
                "0.855681",
                "-0.068507",
                "0.510922",
                "-0.045555"
            ]
        },
        {
            "boneName": "r_upcheek_bone",
            "position": [
                "-0.017676",
                "1.561950",
                "0.112841"
            ],
            "rotation": [
                "0.419905",
                "-0.125121",
                "0.823373",
                "-0.360668"
            ]
        },
        {
            "boneName": "l_headaddside3c_bone",
            "position": [
                "0.073164",
                "1.698042",
                "-0.012646"
            ],
            "rotation": [
                "0.991399",
                "0.024621",
                "-0.119189",
                "0.048123"
            ]
        },
        {
            "boneName": "c_mouthup_bone",
            "position": [
                "-0.001739",
                "1.611848",
                "0.130280"
            ],
            "rotation": [
                "0.703805",
                "-0.038609",
                "0.708772",
                "-0.028474"
            ]
        },
        {
            "boneName": "l_in_mouthup_bone",
            "position": [
                "0.012189",
                "1.611120",
                "0.127720"
            ],
            "rotation": [
                "0.845141",
                "0.121992",
                "0.513443",
                "0.085035"
            ]
        },
        {
            "boneName": "c_down_lipscenter_bone",
            "position": [
                "-0.001393",
                "1.601301",
                "0.122591"
            ],
            "rotation": [
                "0.50464",
                "0.505056",
                "0.479279",
                "0.51044"
            ]
        },
        {
            "boneName": "l_center_eyebrow_bone",
            "position": [
                "0.036357",
                "1.686465",
                "0.119523"
            ],
            "rotation": [
                "0.871957",
                "-0.121555",
                "0.47115",
                "-0.054164"
            ]
        },
        {
            "boneName": "l_up_lipsin_bone",
            "position": [
                "0.007556",
                "1.600296",
                "0.123035"
            ],
            "rotation": [
                "0.560099",
                "-0.60019",
                "0.371766",
                "-0.433418"
            ]
        },
        {
            "boneName": "r_headaddside1a_bone",
            "position": [
                "-0.031656",
                "1.727877",
                "0.109451"
            ],
            "rotation": [
                "-0.517194",
                "-0.105233",
                "-0.82886",
                "-0.185548"
            ]
        },
        {
            "boneName": "c_headaddf_bone",
            "position": [
                "-0.002065",
                "1.674811",
                "-0.071581"
            ],
            "rotation": [
                "0.70976",
                "-0.155189",
                "-0.684955",
                "-0.054716"
            ]
        },
        {
            "boneName": "l_ear_bone",
            "position": [
                "0.076140",
                "1.648091",
                "0.014712"
            ],
            "rotation": [
                "0.987258",
                "-0.091829",
                "0.081516",
                "0.101212"
            ]
        },
        {
            "boneName": "r_masseter_bone",
            "position": [
                "-0.064714",
                "1.607237",
                "0.079608"
            ],
            "rotation": [
                "0.131967",
                "-0.012157",
                "0.984303",
                "-0.11655"
            ]
        },
        {
            "boneName": "c_noseupwrincle_bone",
            "position": [
                "-0.001940",
                "1.672188",
                "0.127157"
            ],
            "rotation": [
                "0.687271",
                "-0.089055",
                "0.718631",
                "-0.057414"
            ]
        },
        {
            "boneName": "r_down_lipsin_bone",
            "position": [
                "-0.010201",
                "1.601044",
                "0.122252"
            ],
            "rotation": [
                "0.412448",
                "0.535999",
                "0.498966",
                "0.541872"
            ]
        },
        {
            "boneName": "l_in_infraorbital_bone",
            "position": [
                "0.022960",
                "1.662384",
                "0.113956"
            ],
            "rotation": [
                "0.609721",
                "-0.069145",
                "0.786762",
                "-0.066817"
            ]
        },
        {
            "boneName": "l_in_forehead_bone",
            "position": [
                "0.017294",
                "1.710204",
                "0.120754"
            ],
            "rotation": [
                "0.778471",
                "0.170751",
                "0.585527",
                "0.148277"
            ]
        },
        {
            "boneName": "l_headaddside1b_bone",
            "position": [
                "0.028439",
                "1.759269",
                "0.074961"
            ],
            "rotation": [
                "0.865225",
                "0.414848",
                "0.281546",
                "0.004252"
            ]
        },
        {
            "boneName": "r_merkel_bone",
            "position": [
                "-0.039231",
                "1.596581",
                "0.110341"
            ],
            "rotation": [
                "0.441971",
                "-0.024515",
                "0.883207",
                "-0.154941"
            ]
        },
        {
            "boneName": "l_temple_bone",
            "position": [
                "0.070071",
                "1.672354",
                "0.054397"
            ],
            "rotation": [
                "0.993524",
                "0.019995",
                "0.076942",
                "0.081174"
            ]
        },
        {
            "boneName": "l_out_eyelidupaimbase_bone",
            "position": [
                "0.029522",
                "1.670949",
                "0.103684"
            ],
            "rotation": [
                "-0.665118",
                "0.221079",
                "-0.240037",
                "-0.671658"
            ]
        },
        {
            "boneName": "l_headaddside1f_bone",
            "position": [
                "0.052560",
                "1.664977",
                "-0.044654"
            ],
            "rotation": [
                "0.919375",
                "-0.058069",
                "-0.367975",
                "0.126378"
            ]
        },
        {
            "boneName": "c_submentalneck_bone",
            "position": [
                "-0.003998",
                "1.552878",
                "0.085760"
            ],
            "rotation": [
                "0.56862",
                "-0.428619",
                "0.565689",
                "-0.415876"
            ]
        },
        {
            "boneName": "l_center_nasolabial_bone",
            "position": [
                "0.041514",
                "1.611437",
                "0.107854"
            ],
            "rotation": [
                "0.922404",
                "-0.09545",
                "0.373323",
                "0.026289"
            ]
        },
        {
            "boneName": "l_up_nasolabial_bone",
            "position": [
                "0.029619",
                "1.628119",
                "0.117261"
            ],
            "rotation": [
                "0.78639",
                "0.006355",
                "0.616451",
                "-0.039222"
            ]
        },
        {
            "boneName": "l_mouthdown_bone",
            "position": [
                "0.023233",
                "1.589751",
                "0.114295"
            ],
            "rotation": [
                "0.874289",
                "-0.154845",
                "0.44259",
                "0.125522"
            ]
        },
        {
            "boneName": "l_down_nasolabial_bone",
            "position": [
                "0.043201",
                "1.581587",
                "0.090417"
            ],
            "rotation": [
                "0.935805",
                "-0.231322",
                "0.257756",
                "-0.065729"
            ]
        },
        {
            "boneName": "l_headaddside1c_bone",
            "position": [
                "0.024533",
                "1.775985",
                "0.030022"
            ],
            "rotation": [
                "0.833692",
                "0.548552",
                "0.060072",
                "-0.020963"
            ]
        },
        {
            "boneName": "c_headadda_bone",
            "position": [
                "-0.001743",
                "1.735099",
                "0.112132"
            ],
            "rotation": [
                "0.679561",
                "0.182439",
                "0.683921",
                "0.192782"
            ]
        },
        {
            "boneName": "r_in_eyelidupaimbase_bone",
            "position": [
                "-0.033060",
                "1.672472",
                "0.103950"
            ],
            "rotation": [
                "-0.64209",
                "0.26671",
                "-0.296177",
                "-0.654879"
            ]
        },
        {
            "boneName": "l_headaddside2b_bone",
            "position": [
                "0.057995",
                "1.738746",
                "0.061147"
            ],
            "rotation": [
                "0.950989",
                "0.258054",
                "0.160488",
                "-0.057204"
            ]
        },
        {
            "boneName": "r_out_eyebrow_bone",
            "position": [
                "-0.053077",
                "1.681920",
                "0.106956"
            ],
            "rotation": [
                "0.333726",
                "-0.060325",
                "0.936343",
                "-0.090825"
            ]
        },
        {
            "boneName": "l_out_eyeliddownaimbase_bone",
            "position": [
                "0.029522",
                "1.670949",
                "0.103684"
            ],
            "rotation": [
                "0.699693",
                "-0.331956",
                "0.102127",
                "0.624344"
            ]
        },
        {
            "boneName": "c_browcenter_bone",
            "position": [
                "-0.002172",
                "1.683839",
                "0.131030"
            ],
            "rotation": [
                "0.682755",
                "-0.056135",
                "0.727276",
                "-0.041997"
            ]
        },
        {
            "boneName": "l_out_infraorbital_bone",
            "position": [
                "0.047037",
                "1.663048",
                "0.102410"
            ],
            "rotation": [
                "0.923706",
                "0.089784",
                "0.370596",
                "0.036945"
            ]
        },
        {
            "boneName": "l_headaddside2c_bone",
            "position": [
                "0.072045",
                "1.727883",
                "0.021917"
            ],
            "rotation": [
                "0.987183",
                "0.147361",
                "0.039827",
                "0.046558"
            ]
        },
        {
            "boneName": "r_headaddside3a_bone",
            "position": [
                "-0.076006",
                "1.659063",
                "0.051008"
            ],
            "rotation": [
                "0.051942",
                "0.015474",
                "0.998039",
                "-0.031304"
            ]
        },
        {
            "boneName": "l_in_eyeliddownaimbase_bone",
            "position": [
                "0.029522",
                "1.670949",
                "0.103684"
            ],
            "rotation": [
                "0.4025",
                "-0.68008",
                "0.581372",
                "0.193627"
            ]
        },
        {
            "boneName": "r_temple_bone",
            "position": [
                "-0.075495",
                "1.676643",
                "0.056158"
            ],
            "rotation": [
                "-0.102841",
                "-0.040045",
                "-0.993891",
                "-0.00036"
            ]
        },
        {
            "boneName": "l_cen_infraorbital_bone",
            "position": [
                "0.036809",
                "1.661309",
                "0.111926"
            ],
            "rotation": [
                "0.860999",
                "-0.035212",
                "0.503588",
                "-0.061974"
            ]
        },
        {
            "boneName": "c_headaddc_bone",
            "position": [
                "-0.002643",
                "1.778133",
                "0.044100"
            ],
            "rotation": [
                "-0.089439",
                "0.073314",
                "-0.707384",
                "-0.697305"
            ]
        },
        {
            "boneName": "l_merkel_bone",
            "position": [
                "0.035143",
                "1.595841",
                "0.108800"
            ],
            "rotation": [
                "0.894244",
                "-0.177067",
                "0.410349",
                "-0.024257"
            ]
        },
        {
            "boneName": "c_headadde_bone",
            "position": [
                "-0.002294",
                "1.733121",
                "-0.061723"
            ],
            "rotation": [
                "0.577266",
                "-0.064421",
                "-0.699519",
                "-0.416278"
            ]
        },
        {
            "boneName": "l_cen_eyeliddownaimbase_bone",
            "position": [
                "0.029522",
                "1.670949",
                "0.103684"
            ],
            "rotation": [
                "0.644132",
                "-0.554412",
                "0.291709",
                "0.438893"
            ]
        },
        {
            "boneName": "r_angulioris_bone",
            "position": [
                "-0.035579",
                "1.585231",
                "0.108666"
            ],
            "rotation": [
                "0.438439",
                "0.041626",
                "0.879162",
                "-0.181971"
            ]
        },
        {
            "boneName": "l_eyeout_wrinkle_bone",
            "position": [
                "0.047382",
                "1.672801",
                "0.105285"
            ],
            "rotation": [
                "0.89517",
                "-0.247979",
                "0.353856",
                "-0.109373"
            ]
        },
        {
            "boneName": "r_out_forehead_bone",
            "position": [
                "-0.054249",
                "1.704223",
                "0.101224"
            ],
            "rotation": [
                "-0.271547",
                "-0.001925",
                "-0.961152",
                "-0.049448"
            ]
        },
        {
            "boneName": "r_headaddside1d_bone",
            "position": [
                "-0.057974",
                "1.754725",
                "-0.001178"
            ],
            "rotation": [
                "0.09923",
                "-0.044055",
                "-0.937132",
                "-0.331656"
            ]
        },
        {
            "boneName": "r_down_lipsout_bone",
            "position": [
                "-0.017975",
                "1.600586",
                "0.118633"
            ],
            "rotation": [
                "0.386205",
                "0.451071",
                "0.555154",
                "0.582395"
            ]
        },
        {
            "boneName": "r_headaddside1b_bone",
            "position": [
                "-0.030103",
                "1.760108",
                "0.075616"
            ],
            "rotation": [
                "-0.28254",
                "-0.032474",
                "-0.851992",
                "-0.439575"
            ]
        },
        {
            "boneName": "r_in_mouthup_bone",
            "position": [
                "-0.015155",
                "1.611590",
                "0.128958"
            ],
            "rotation": [
                "-0.538731",
                "-0.065172",
                "-0.835452",
                "-0.086836"
            ]
        },
        {
            "boneName": "l_headaddside1d_bone",
            "position": [
                "0.055420",
                "1.754744",
                "-0.001299"
            ],
            "rotation": [
                "0.938",
                "0.329217",
                "-0.098887",
                "0.044653"
            ]
        },
        {
            "boneName": "l_masseter_bone",
            "position": [
                "0.059545",
                "1.606088",
                "0.078066"
            ],
            "rotation": [
                "0.977393",
                "-0.130552",
                "0.166281",
                "-0.003127"
            ]
        },
        {
            "boneName": "r_headaddzygoma_bone",
            "position": [
                "-0.056679",
                "1.647752",
                "0.102316"
            ],
            "rotation": [
                "-0.390738",
                "-0.020173",
                "-0.919849",
                "-0.028193"
            ]
        },
        {
            "boneName": "l_headaddside3b_bone",
            "position": [
                "0.076563",
                "1.682389",
                "0.014736"
            ],
            "rotation": [
                "0.999819",
                "0.001308",
                "-0.009438",
                "-0.016468"
            ]
        },
        {
            "boneName": "r_down_mouthcorner_bone",
            "position": [
                "-0.023919",
                "1.599829",
                "0.113846"
            ],
            "rotation": [
                "0.518237",
                "0.669835",
                "0.4042",
                "0.345506"
            ]
        },
        {
            "boneName": "r_center_nasolabial_bone",
            "position": [
                "-0.045912",
                "1.612402",
                "0.109571"
            ],
            "rotation": [
                "0.406077",
                "0.020486",
                "0.909446",
                "-0.087124"
            ]
        },
        {
            "boneName": "r_mouthdown_bone",
            "position": [
                "-0.027106",
                "1.590633",
                "0.115598"
            ],
            "rotation": [
                "0.46591",
                "0.121141",
                "0.865868",
                "-0.13611"
            ]
        },
        {
            "boneName": "r_headaddside2b_bone",
            "position": [
                "-0.060366",
                "1.740465",
                "0.061910"
            ],
            "rotation": [
                "-0.153598",
                "0.023209",
                "-0.944503",
                "-0.289452"
            ]
        },
        {
            "boneName": "r_headaddside2c_bone",
            "position": [
                "-0.074874",
                "1.728580",
                "0.021670"
            ],
            "rotation": [
                "-0.020332",
                "-0.077222",
                "-0.985407",
                "-0.150319"
            ]
        },
        {
            "boneName": "r_out_mouthup_bone",
            "position": [
                "-0.028780",
                "1.606554",
                "0.121229"
            ],
            "rotation": [
                "0.520501",
                "-0.0609",
                "0.849294",
                "-0.063785"
            ]
        },
        {
            "boneName": "l_up_lipsout_bone",
            "position": [
                "0.014882",
                "1.599786",
                "0.118804"
            ],
            "rotation": [
                "0.592271",
                "-0.631674",
                "0.370361",
                "-0.336209"
            ]
        },
        {
            "boneName": "l_in_eyebrow_bone",
            "position": [
                "0.017121",
                "1.684238",
                "0.128705"
            ],
            "rotation": [
                "0.791174",
                "-0.223039",
                "0.551396",
                "-0.142337"
            ]
        },
        {
            "boneName": "l_nostril_bone",
            "position": [
                "0.014903",
                "1.631211",
                "0.128922"
            ],
            "rotation": [
                "0.954247",
                "0.042904",
                "0.205627",
                "-0.212813"
            ]
        },
        {
            "boneName": "c_tongue4_bone",
            "position": [
                "-0.001916",
                "1.597129",
                "0.112652"
            ],
            "rotation": [
                "0.678527",
                "0.199002",
                "0.678527",
                "0.199001"
            ]
        },
        {
            "boneName": "r_headaddside2a_bone",
            "position": [
                "-0.065266",
                "1.699788",
                "0.080657"
            ],
            "rotation": [
                "-0.229329",
                "-0.010993",
                "-0.972339",
                "-0.04294"
            ]
        },
        {
            "boneName": "l_out_eyebrow_bone",
            "position": [
                "0.049755",
                "1.680472",
                "0.107382"
            ],
            "rotation": [
                "0.929957",
                "-0.108886",
                "0.348099",
                "-0.046385"
            ]
        },
        {
            "boneName": "jawaimbase_bone",
            "position": [
                "-0.000887",
                "1.611415",
                "0.021820"
            ],
            "rotation": [
                "0.559046",
                "-0.563863",
                "0.432976",
                "0.426683"
            ]
        },
        {
            "boneName": "r_up_mouthcorner_bone",
            "position": [
                "-0.023913",
                "1.599636",
                "0.114169"
            ],
            "rotation": [
                "0.471982",
                "-0.537935",
                "0.457172",
                "-0.528066"
            ]
        },
        {
            "boneName": "r_ear_bone",
            "position": [
                "-0.078972",
                "1.648243",
                "0.014754"
            ],
            "rotation": [
                "0.081511",
                "0.101195",
                "0.987261",
                "-0.091826"
            ]
        },
        {
            "boneName": "l_infraorbitalfurrow_bone",
            "position": [
                "0.053753",
                "1.629450",
                "0.098232"
            ],
            "rotation": [
                "0.949481",
                "-0.085457",
                "0.301873",
                "-0.007445"
            ]
        },
        {
            "boneName": "r_cen_infraorbital_bone",
            "position": [
                "-0.040872",
                "1.663342",
                "0.112644"
            ],
            "rotation": [
                "0.512153",
                "-0.062498",
                "0.85626",
                "-0.024723"
            ]
        },
        {
            "boneName": "l_headaddbangs_bone",
            "position": [
                "0.047334",
                "1.689754",
                "0.110053"
            ],
            "rotation": [
                "0.940206",
                "0.073832",
                "0.329731",
                "0.04287"
            ]
        },
        {
            "boneName": "r_headaddside1g_bone",
            "position": [
                "-0.051271",
                "1.620912",
                "-0.024465"
            ],
            "rotation": [
                "-0.331818",
                "0.099192",
                "0.926915",
                "-0.144524"
            ]
        },
        {
            "boneName": "r_headaddside1c_bone",
            "position": [
                "-0.026946",
                "1.775771",
                "0.030195"
            ],
            "rotation": [
                "-0.063448",
                "0.021251",
                "-0.832416",
                "-0.550097"
            ]
        },
        {
            "boneName": "l_headaddside1a_bone",
            "position": [
                "0.029484",
                "1.726492",
                "0.109063"
            ],
            "rotation": [
                "0.824317",
                "0.169623",
                "0.528793",
                "0.110033"
            ]
        },
        {
            "boneName": "l_cen_eyelidupaimbase_bone",
            "position": [
                "0.029522",
                "1.670949",
                "0.103684"
            ],
            "rotation": [
                "-0.462403",
                "0.400185",
                "-0.534962",
                "-0.582968"
            ]
        },
        {
            "boneName": "r_up_lipsin_bone",
            "position": [
                "-0.010402",
                "1.600525",
                "0.123596"
            ],
            "rotation": [
                "0.389545",
                "-0.452922",
                "0.535756",
                "-0.596725"
            ]
        },
        {
            "boneName": "c_headaddb_bone",
            "position": [
                "-0.001801",
                "1.755463",
                "0.094834"
            ],
            "rotation": [
                "0.652672",
                "0.282643",
                "0.635415",
                "0.300635"
            ]
        },
        {
            "boneName": "r_out_eyelidupaimbase_bone",
            "position": [
                "-0.033060",
                "1.672472",
                "0.103950"
            ],
            "rotation": [
                "-0.20966",
                "0.668178",
                "-0.675309",
                "-0.231383"
            ]
        },
        {
            "boneName": "c_tonguetop_bone",
            "position": [
                "-0.001915",
                "1.610180",
                "0.072009"
            ],
            "rotation": [
                "0.520878",
                "0.478212",
                "0.520878",
                "0.478212"
            ]
        },
        {
            "boneName": "l_infraorbitalfurrowup_bone",
            "position": [
                "0.046936",
                "1.646390",
                "0.107062"
            ],
            "rotation": [
                "0.871054",
                "0.021029",
                "0.488918",
                "0.042208"
            ]
        },
        {
            "boneName": "l_cheek_bone",
            "position": [
                "0.064173",
                "1.603342",
                "0.039708"
            ],
            "rotation": [
                "0.984895",
                "-0.16112",
                "0.057433",
                "0.026912"
            ]
        },
        {
            "boneName": "r_infraorbitalfurrowup_bone",
            "position": [
                "-0.050541",
                "1.647662",
                "0.106919"
            ],
            "rotation": [
                "-0.480913",
                "-0.056646",
                "-0.874176",
                "-0.036481"
            ]
        },
        {
            "boneName": "r_headaddside1e_bone",
            "position": [
                "-0.063004",
                "1.720422",
                "-0.034245"
            ],
            "rotation": [
                "0.276639",
                "-0.050677",
                "-0.950308",
                "-0.13348"
            ]
        },
        {
            "boneName": "r_up_lipsout_bone",
            "position": [
                "-0.017662",
                "1.599892",
                "0.119758"
            ],
            "rotation": [
                "0.354623",
                "-0.329278",
                "0.554218",
                "-0.677245"
            ]
        },
        {
            "boneName": "c_headaddd_bone",
            "position": [
                "-0.002568",
                "1.770211",
                "-0.025035"
            ],
            "rotation": [
                "0.246354",
                "-0.140993",
                "-0.693231",
                "-0.662466"
            ]
        },
        {
            "boneName": "l_headaddside3a_bone",
            "position": [
                "0.071311",
                "1.655337",
                "0.050039"
            ],
            "rotation": [
                "0.99718",
                "-0.023555",
                "0.05066",
                "0.050109"
            ]
        },
        {
            "boneName": "l_up_mouthcorner_bone",
            "position": [
                "0.021392",
                "1.599344",
                "0.113954"
            ],
            "rotation": [
                "0.471235",
                "-0.398651",
                "0.589395",
                "-0.521179"
            ]
        },
        {
            "boneName": "r_cheek_bone",
            "position": [
                "-0.068482",
                "1.604579",
                "0.040371"
            ],
            "rotation": [
                "0.038215",
                "0.017174",
                "0.988575",
                "-0.14479"
            ]
        },
        {
            "boneName": "r_headaddside3b_bone",
            "position": [
                "-0.078929",
                "1.682506",
                "0.014691"
            ],
            "rotation": [
                "0.012972",
                "0.002691",
                "-0.999861",
                "-0.010075"
            ]
        },
        {
            "boneName": "r_in_forehead_bone",
            "position": [
                "-0.020200",
                "1.711297",
                "0.121484"
            ],
            "rotation": [
                "0.592473",
                "0.141615",
                "0.77006",
                "0.189548"
            ]
        },
        {
            "boneName": "r_nose_nasolabial_bone",
            "position": [
                "-0.025353",
                "1.644513",
                "0.119054"
            ],
            "rotation": [
                "-0.543632",
                "0.010376",
                "-0.82062",
                "-0.175897"
            ]
        },
        {
            "boneName": "r_headaddside3d_bone",
            "position": [
                "-0.070602",
                "1.650062",
                "-0.010176"
            ],
            "rotation": [
                "-0.166854",
                "0.088078",
                "0.975504",
                "-0.113111"
            ]
        }
    ]
}