{
    "materialsData": [
        {
            "number": 1,
            "name": "sh_scan_wmn_007.mat"
        },
        {
            "number": 2,
            "name": "sh_eye.mat"
        },
        {
            "number": 3,
            "name": "sh_mouth_interior.mat"
        },
        {
            "number": 4,
            "name": "sh_eyelashes.mat"
        },
        {
            "number": 5,
            "name": "sh_eye_shadow.mat"
        },
        {
            "number": 6,
            "name": "sh_wet_eye.mat"
        }
    ],
    "variations": {
        "1": [
            {
                "number": 1,
                "name": "sh_scan_wmn_007.mat"
            },
            {
                "number": 2,
                "name": "sh_eye.mat"
            },
            {
                "number": 3,
                "name": "sh_mouth_interior.mat"
            },
            {
                "number": 4,
                "name": "sh_eyelashes.mat"
            },
            {
                "number": 5,
                "name": "sh_eye_shadow.mat"
            },
            {
                "number": 6,
                "name": "sh_wet_eye.mat"
            }
        ],
        "2": [
            {
                "number": 1,
                "name": "sh_scan_wmn_007.mat"
            },
            {
                "number": 2,
                "name": "sh_eye_green.mat"
            },
            {
                "number": 3,
                "name": "sh_mouth_interior.mat"
            },
            {
                "number": 4,
                "name": "sh_eyelashes.mat"
            },
            {
                "number": 5,
                "name": "sh_eye_shadow.mat"
            },
            {
                "number": 6,
                "name": "sh_wet_eye.mat"
            }
        ],
        "3": [
            {
                "number": 1,
                "name": "sh_mother_3.mat"
            },
            {
                "number": 2,
                "name": "sh_eye_grey.mat"
            },
            {
                "number": 3,
                "name": "sh_mouth_interior.mat"
            },
            {
                "number": 4,
                "name": "sh_eyelashes.mat"
            },
            {
                "number": 5,
                "name": "sh_eye_shadow.mat"
            },
            {
                "number": 6,
                "name": "sh_wet_eye.mat"
            }
        ],
        "4": [
            {
                "number": 1,
                "name": "sh_wmn_a.mat"
            },
            {
                "number": 2,
                "name": "sh_eye_green.mat"
            },
            {
                "number": 3,
                "name": "sh_mouth_interior.mat"
            },
            {
                "number": 4,
                "name": "sh_eyelashes.mat"
            },
            {
                "number": 5,
                "name": "sh_eye_shadow.mat"
            },
            {
                "number": 6,
                "name": "sh_wet_eye.mat"
            }
        ],
        "5": [
            {
                "number": 1,
                "name": "sh_scan_wmn_007.mat"
            },
            {
                "number": 2,
                "name": "sh_eye.mat"
            },
            {
                "number": 3,
                "name": "sh_mouth_interior.mat"
            },
            {
                "number": 4,
                "name": "sh_eyelashes.mat"
            },
            {
                "number": 5,
                "name": "sh_eye_shadow.mat"
            },
            {
                "number": 6,
                "name": "sh_wet_eye.mat"
            }
        ],
        "6": [
            {
                "number": 1,
                "name": "sh_scan_wmn_007.mat"
            },
            {
                "number": 2,
                "name": "sh_eye_green.mat"
            },
            {
                "number": 3,
                "name": "sh_mouth_interior.mat"
            },
            {
                "number": 4,
                "name": "sh_eyelashes.mat"
            },
            {
                "number": 5,
                "name": "sh_eye_shadow.mat"
            },
            {
                "number": 6,
                "name": "sh_wet_eye.mat"
            }
        ],
        "7": [
            {
                "number": 1,
                "name": "sh_mother_3.mat"
            },
            {
                "number": 2,
                "name": "sh_eye_degenerated.mat"
            },
            {
                "number": 3,
                "name": "sh_mouth_interior_zmb.mat"
            },
            {
                "number": 4,
                "name": "sh_eyelashes.mat"
            },
            {
                "number": 5,
                "name": "sh_eye_shadow.mat"
            },
            {
                "number": 6,
                "name": "sh_wet_eye.mat"
            }
        ],
        "8": [
            {
                "number": 1,
                "name": "sh_biter_b.mat"
            },
            {
                "number": 2,
                "name": "sh_eye_degenerated.mat"
            },
            {
                "number": 3,
                "name": "sh_mouth_interior_zmb.mat"
            },
            {
                "number": 4,
                "name": "sh_eyelashes.mat"
            },
            {
                "number": 5,
                "name": "sh_eye_shadow.mat"
            },
            {
                "number": 6,
                "name": "sh_wet_eye.mat"
            }
        ],
        "9": [
            {
                "number": 1,
                "name": "sh_biter_a.mat"
            },
            {
                "number": 2,
                "name": "sh_eye_degenerated.mat"
            },
            {
                "number": 3,
                "name": "sh_mouth_interior_zmb.mat"
            },
            {
                "number": 4,
                "name": "sh_eyelashes.mat"
            },
            {
                "number": 5,
                "name": "sh_eye_shadow.mat"
            },
            {
                "number": 6,
                "name": "sh_wet_eye.mat"
            }
        ],
        "10": [
            {
                "number": 1,
                "name": "sh_scan_wmn_010.mat"
            },
            {
                "number": 2,
                "name": "sh_eye.mat"
            },
            {
                "number": 3,
                "name": "sh_mouth_interior.mat"
            },
            {
                "number": 4,
                "name": "sh_eyelashes.mat"
            },
            {
                "number": 5,
                "name": "sh_eye_shadow.mat"
            },
            {
                "number": 6,
                "name": "sh_wet_eye.mat"
            }
        ]
    },
    "bones": [
        {
            "boneName": "scan_wmn_007_lod_0",
            "position": [
                "0.000000",
                "0.000000",
                "0.000000"
            ],
            "rotation": [
                "0",
                "0",
                "0",
                "1"
            ]
        },
        {
            "boneName": "spine3",
            "position": [
                "0.000011",
                "1.238883",
                "-0.060143"
            ],
            "rotation": [
                "0.707107",
                "0.707107",
                "0.000231",
                "-0.000596"
            ]
        },
        {
            "boneName": "l_clavicle",
            "position": [
                "0.040334",
                "1.409394",
                "-0.005880"
            ],
            "rotation": [
                "0.946929",
                "0.204522",
                "-0.244457",
                "-0.041688"
            ]
        },
        {
            "boneName": "r_clavicle",
            "position": [
                "-0.040257",
                "1.409394",
                "-0.005839"
            ],
            "rotation": [
                "0.204544",
                "0.947054",
                "0.041584",
                "0.243969"
            ]
        },
        {
            "boneName": "neck",
            "position": [
                "0.000014",
                "1.463681",
                "-0.050272"
            ],
            "rotation": [
                "0.696227",
                "0.696316",
                "0.123143",
                "-0.123483"
            ]
        },
        {
            "boneName": "neck1",
            "position": [
                "0.000011",
                "1.537261",
                "-0.023365"
            ],
            "rotation": [
                "0.701134",
                "0.70125",
                "0.091078",
                "-0.091458"
            ]
        },
        {
            "boneName": "head",
            "position": [
                "0.000004",
                "1.609498",
                "-0.004236"
            ],
            "rotation": [
                "0.707107",
                "0.707107",
                "0.000231",
                "-0.000595"
            ]
        },
        {
            "boneName": "headend",
            "position": [
                "0.000004",
                "1.609498",
                "-0.004236"
            ],
            "rotation": [
                "0.707107",
                "0.707107",
                "0.000231",
                "-0.000595"
            ]
        },
        {
            "boneName": "r_eye_pos",
            "position": [
                "0.000004",
                "1.609498",
                "-0.004236"
            ],
            "rotation": [
                "0.707107",
                "0.707107",
                "0.000231",
                "-0.000595"
            ]
        },
        {
            "boneName": "l_eye_pos",
            "position": [
                "0.000004",
                "1.609498",
                "-0.004236"
            ],
            "rotation": [
                "0.707107",
                "0.707107",
                "0.000231",
                "-0.000595"
            ]
        },
        {
            "boneName": "r_down_front_lipsin_bone",
            "position": [
                "-0.003860",
                "1.590574",
                "0.106019"
            ],
            "rotation": [
                "-0.592188",
                "-0.061733",
                "-0.799019",
                "-0.084093"
            ]
        },
        {
            "boneName": "r_out_mouthcorner_bone",
            "position": [
                "-0.020695",
                "1.595139",
                "0.092027"
            ],
            "rotation": [
                "0.402912",
                "0.406474",
                "0.811626",
                "-0.117067"
            ]
        },
        {
            "boneName": "l_down_front_lipsin_bone",
            "position": [
                "0.007723",
                "1.590690",
                "0.105919"
            ],
            "rotation": [
                "0.792888",
                "0.089066",
                "0.602342",
                "0.024098"
            ]
        },
        {
            "boneName": "l_centercheek_bone",
            "position": [
                "0.052164",
                "1.606659",
                "0.073689"
            ],
            "rotation": [
                "0.957965",
                "-0.094755",
                "0.259126",
                "-0.078607"
            ]
        },
        {
            "boneName": "r_center_nasolabialcrease_bone",
            "position": [
                "-0.033458",
                "1.605628",
                "0.090590"
            ],
            "rotation": [
                "0.471724",
                "-0.048726",
                "0.875952",
                "-0.088374"
            ]
        },
        {
            "boneName": "l_up_front_lipsin_bone",
            "position": [
                "0.006454",
                "1.597830",
                "0.106174"
            ],
            "rotation": [
                "0.752132",
                "-0.274904",
                "0.515564",
                "-0.304827"
            ]
        },
        {
            "boneName": "l_nosecorner_bone",
            "position": [
                "0.018551",
                "1.627138",
                "0.099690"
            ],
            "rotation": [
                "0.810165",
                "0.026736",
                "0.576877",
                "-0.100647"
            ]
        },
        {
            "boneName": "l_down_front_lipsout_bone",
            "position": [
                "0.018025",
                "1.593750",
                "0.099732"
            ],
            "rotation": [
                "0.852574",
                "0.024865",
                "0.421785",
                "0.307564"
            ]
        },
        {
            "boneName": "r_zygoma_bone",
            "position": [
                "-0.044996",
                "1.632143",
                "0.088173"
            ],
            "rotation": [
                "0.400109",
                "-0.027215",
                "0.916056",
                "-0.003609"
            ]
        },
        {
            "boneName": "l_center_nasolabialcrease_bone",
            "position": [
                "0.035946",
                "1.606260",
                "0.090780"
            ],
            "rotation": [
                "0.895488",
                "-0.047229",
                "0.439607",
                "-0.051149"
            ]
        },
        {
            "boneName": "l_mandible_bone",
            "position": [
                "0.032773",
                "1.569735",
                "0.075878"
            ],
            "rotation": [
                "0.926004",
                "-0.263026",
                "0.259258",
                "-0.078228"
            ]
        },
        {
            "boneName": "l_out_mouthcorner_bone",
            "position": [
                "0.024426",
                "1.595712",
                "0.091331"
            ],
            "rotation": [
                "0.792355",
                "-0.060626",
                "0.384912",
                "0.469404"
            ]
        },
        {
            "boneName": "r_up_front_lipsin_bone",
            "position": [
                "-0.004887",
                "1.597853",
                "0.106491"
            ],
            "rotation": [
                "0.535214",
                "-0.313039",
                "0.739637",
                "-0.261704"
            ]
        },
        {
            "boneName": "r_up_front_lipsout_bone",
            "position": [
                "-0.014282",
                "1.598436",
                "0.102669"
            ],
            "rotation": [
                "0.488517",
                "-0.240749",
                "0.787961",
                "-0.287245"
            ]
        },
        {
            "boneName": "r_in_browup_bone",
            "position": [
                "-0.029106",
                "1.698512",
                "0.102492"
            ],
            "rotation": [
                "-0.535038",
                "-0.067453",
                "-0.83867",
                "-0.076272"
            ]
        },
        {
            "boneName": "l_up_front_lipsout_bone",
            "position": [
                "0.016240",
                "1.598614",
                "0.101662"
            ],
            "rotation": [
                "0.783286",
                "-0.314361",
                "0.462072",
                "-0.272268"
            ]
        },
        {
            "boneName": "c_centerchin_bone",
            "position": [
                "0.002701",
                "1.566053",
                "0.097393"
            ],
            "rotation": [
                "0.712587",
                "-0.041053",
                "0.696679",
                "-0.071923"
            ]
        },
        {
            "boneName": "l_mouthcorner_bone",
            "position": [
                "0.023761",
                "1.598319",
                "0.092971"
            ],
            "rotation": [
                "0.75382",
                "-0.418563",
                "0.360063",
                "-0.356251"
            ]
        },
        {
            "boneName": "r_nosecorner_bone",
            "position": [
                "-0.017446",
                "1.628089",
                "0.098453"
            ],
            "rotation": [
                "0.646254",
                "-0.091498",
                "0.757369",
                "-0.019395"
            ]
        },
        {
            "boneName": "l_zygoma_bone",
            "position": [
                "0.046896",
                "1.632619",
                "0.089482"
            ],
            "rotation": [
                "0.910323",
                "0.010651",
                "0.41252",
                "-0.032042"
            ]
        },
        {
            "boneName": "l_up_nasolabialcrease_bone",
            "position": [
                "0.026963",
                "1.618285",
                "0.096871"
            ],
            "rotation": [
                "0.769823",
                "0.00509",
                "0.627796",
                "-0.11497"
            ]
        },
        {
            "boneName": "l_in_browup_bone",
            "position": [
                "0.030556",
                "1.698032",
                "0.101737"
            ],
            "rotation": [
                "0.838745",
                "0.106321",
                "0.529915",
                "0.066285"
            ]
        },
        {
            "boneName": "r_mandible_bone",
            "position": [
                "-0.027902",
                "1.568714",
                "0.076267"
            ],
            "rotation": [
                "0.245265",
                "-0.09871",
                "0.923426",
                "-0.278184"
            ]
        },
        {
            "boneName": "r_in_browdown_bone",
            "position": [
                "-0.018671",
                "1.676209",
                "0.102303"
            ],
            "rotation": [
                "0.553196",
                "-0.195141",
                "0.759973",
                "-0.279885"
            ]
        },
        {
            "boneName": "l_in_browdown_bone",
            "position": [
                "0.020817",
                "1.676361",
                "0.100413"
            ],
            "rotation": [
                "0.796693",
                "-0.313717",
                "0.487225",
                "-0.171676"
            ]
        },
        {
            "boneName": "r_centercheek_bone",
            "position": [
                "-0.049168",
                "1.605550",
                "0.073951"
            ],
            "rotation": [
                "0.252912",
                "-0.083404",
                "0.958935",
                "-0.097587"
            ]
        },
        {
            "boneName": "r_mouthcorner_bone",
            "position": [
                "-0.020930",
                "1.597286",
                "0.094520"
            ],
            "rotation": [
                "0.354084",
                "-0.349529",
                "0.790067",
                "-0.358118"
            ]
        },
        {
            "boneName": "r_down_front_lipsout_bone",
            "position": [
                "-0.013756",
                "1.592975",
                "0.099790"
            ],
            "rotation": [
                "0.423091",
                "0.348716",
                "0.836291",
                "0.002832"
            ]
        },
        {
            "boneName": "r_up_nasolabialcrease_bone",
            "position": [
                "-0.025412",
                "1.618218",
                "0.096239"
            ],
            "rotation": [
                "0.669037",
                "-0.116248",
                "0.733328",
                "-0.033251"
            ]
        },
        {
            "boneName": "l_angulioris_bone",
            "position": [
                "0.033853",
                "1.584344",
                "0.084807"
            ],
            "rotation": [
                "0.875281",
                "-0.200051",
                "0.439198",
                "-0.031107"
            ]
        },
        {
            "boneName": "l_upcheek_bone",
            "position": [
                "0.017419",
                "1.561266",
                "0.088434"
            ],
            "rotation": [
                "0.867774",
                "-0.305657",
                "0.366989",
                "-0.137334"
            ]
        },
        {
            "boneName": "r_infraorbitalfurrow_bone",
            "position": [
                "-0.053133",
                "1.629193",
                "0.077679"
            ],
            "rotation": [
                "0.282019",
                "-0.057265",
                "0.954305",
                "-0.080547"
            ]
        },
        {
            "boneName": "l_in_eyelidupaimbase_bone",
            "position": [
                "0.033045",
                "1.668441",
                "0.082970"
            ],
            "rotation": [
                "-0.267704",
                "0.649925",
                "-0.654473",
                "-0.278564"
            ]
        },
        {
            "boneName": "l_headaddside2a_bone",
            "position": [
                "0.062887",
                "1.700705",
                "0.063442"
            ],
            "rotation": [
                "0.981289",
                "0.021248",
                "0.188657",
                "-0.03208"
            ]
        },
        {
            "boneName": "r_out_eyeliddownaimbase_bone",
            "position": [
                "-0.031271",
                "1.668583",
                "0.085065"
            ],
            "rotation": [
                "0.318458",
                "-0.706606",
                "0.631336",
                "0.026612"
            ]
        },
        {
            "boneName": "c_up_lipscenter_bone",
            "position": [
                "0.000718",
                "1.595323",
                "0.102644"
            ],
            "rotation": [
                "0.418998",
                "-0.58249",
                "0.400299",
                "-0.570006"
            ]
        },
        {
            "boneName": "l_in_mouthdown_bone",
            "position": [
                "0.015248",
                "1.585380",
                "0.099826"
            ],
            "rotation": [
                "0.86746",
                "-0.289828",
                "0.39319",
                "-0.09442"
            ]
        },
        {
            "boneName": "l_headaddside1e_bone",
            "position": [
                "0.062957",
                "1.720858",
                "-0.046726"
            ],
            "rotation": [
                "0.948936",
                "0.150026",
                "-0.275446",
                "0.033805"
            ]
        },
        {
            "boneName": "r_headaddside3c_bone",
            "position": [
                "-0.071960",
                "1.696857",
                "-0.025773"
            ],
            "rotation": [
                "0.106119",
                "-0.043657",
                "-0.993381",
                "-0.005148"
            ]
        },
        {
            "boneName": "r_headaddside1f_bone",
            "position": [
                "-0.052747",
                "1.665014",
                "-0.058682"
            ],
            "rotation": [
                "-0.334004",
                "0.104548",
                "0.934482",
                "-0.065226"
            ]
        },
        {
            "boneName": "l_down_mouthcorner_bone",
            "position": [
                "0.023130",
                "1.597733",
                "0.089907"
            ],
            "rotation": [
                "0.496767",
                "0.445007",
                "0.494275",
                "0.55757"
            ]
        },
        {
            "boneName": "c_submental_bone",
            "position": [
                "0.002666",
                "1.554415",
                "0.081034"
            ],
            "rotation": [
                "0.577471",
                "-0.454518",
                "0.523361",
                "-0.431318"
            ]
        },
        {
            "boneName": "l_nose_nasolabial_bone",
            "position": [
                "0.022947",
                "1.640647",
                "0.098394"
            ],
            "rotation": [
                "0.811528",
                "0.175927",
                "0.556443",
                "0.02902"
            ]
        },
        {
            "boneName": "c_headaddg_bone",
            "position": [
                "0.001419",
                "1.616222",
                "-0.066673"
            ],
            "rotation": [
                "-0.690723",
                "0.118047",
                "0.705812",
                "-0.103906"
            ]
        },
        {
            "boneName": "c_endnose_bone",
            "position": [
                "-0.001564",
                "1.629680",
                "0.126821"
            ],
            "rotation": [
                "-0.699338",
                "0.00047",
                "-0.714717",
                "-0.010334"
            ]
        },
        {
            "boneName": "l_headaddside1g_bone",
            "position": [
                "0.054281",
                "1.618676",
                "-0.041010"
            ],
            "rotation": [
                "0.936935",
                "-0.128761",
                "-0.302321",
                "0.119058"
            ]
        },
        {
            "boneName": "r_headaddbangs_bone",
            "position": [
                "-0.048898",
                "1.689382",
                "0.091303"
            ],
            "rotation": [
                "-0.320272",
                "-0.01574",
                "-0.945078",
                "-0.063293"
            ]
        },
        {
            "boneName": "r_eyeup_wrinkle_bone",
            "position": [
                "-0.033047",
                "1.678358",
                "0.099065"
            ],
            "rotation": [
                "0.589578",
                "-0.178838",
                "0.759284",
                "-0.20953"
            ]
        },
        {
            "boneName": "r_center_eyebrow_bone",
            "position": [
                "-0.038558",
                "1.685644",
                "0.101098"
            ],
            "rotation": [
                "0.498289",
                "-0.04259",
                "0.862278",
                "-0.079825"
            ]
        },
        {
            "boneName": "r_up_nasolabial_bone",
            "position": [
                "-0.029440",
                "1.626559",
                "0.097687"
            ],
            "rotation": [
                "0.644022",
                "-0.032347",
                "0.763402",
                "-0.037502"
            ]
        },
        {
            "boneName": "l_headaddside3d_bone",
            "position": [
                "0.070159",
                "1.652755",
                "-0.023129"
            ],
            "rotation": [
                "0.986282",
                "-0.107605",
                "-0.053674",
                "0.113088"
            ]
        },
        {
            "boneName": "l_tongue3_bone",
            "position": [
                "0.016179",
                "1.591925",
                "0.075978"
            ],
            "rotation": [
                "0.746558",
                "-0.244736",
                "-0.090066",
                "0.612081"
            ]
        },
        {
            "boneName": "r_down_nasolabial_bone",
            "position": [
                "-0.041810",
                "1.582572",
                "0.069952"
            ],
            "rotation": [
                "0.238634",
                "-0.105509",
                "0.93455",
                "-0.241947"
            ]
        },
        {
            "boneName": "l_tongue2_bone",
            "position": [
                "0.020414",
                "1.597070",
                "0.052331"
            ],
            "rotation": [
                "-0.671672",
                "-0.011472",
                "-0.050005",
                "-0.73907"
            ]
        },
        {
            "boneName": "l_eyeup_wrinkle_bone",
            "position": [
                "0.035653",
                "1.678056",
                "0.095075"
            ],
            "rotation": [
                "0.752157",
                "-0.26053",
                "0.558525",
                "-0.233311"
            ]
        },
        {
            "boneName": "r_in_eyeliddownaimbase_bone",
            "position": [
                "-0.031271",
                "1.668583",
                "0.085065"
            ],
            "rotation": [
                "0.699303",
                "-0.443557",
                "0.104766",
                "0.550688"
            ]
        },
        {
            "boneName": "c_centerchinup_bone",
            "position": [
                "0.001808",
                "1.581487",
                "0.099281"
            ],
            "rotation": [
                "0.655124",
                "-0.278934",
                "0.639206",
                "-0.290558"
            ]
        },
        {
            "boneName": "r_in_eyebrow_bone",
            "position": [
                "-0.017535",
                "1.682764",
                "0.106904"
            ],
            "rotation": [
                "0.648072",
                "-0.094938",
                "0.743655",
                "-0.134039"
            ]
        },
        {
            "boneName": "r_out_infraorbital_bone",
            "position": [
                "-0.048019",
                "1.660829",
                "0.081797"
            ],
            "rotation": [
                "-0.304691",
                "0.079499",
                "-0.947778",
                "-0.050603"
            ]
        },
        {
            "boneName": "l_headaddzygoma_bone",
            "position": [
                "0.053949",
                "1.645772",
                "0.082203"
            ],
            "rotation": [
                "0.924366",
                "0.077008",
                "0.373221",
                "-0.017973"
            ]
        },
        {
            "boneName": "r_in_infraorbital_bone",
            "position": [
                "-0.024805",
                "1.658446",
                "0.095195"
            ],
            "rotation": [
                "0.766668",
                "0.055058",
                "0.638371",
                "0.040891"
            ]
        },
        {
            "boneName": "l_down_lipsout_bone",
            "position": [
                "0.017859",
                "1.597474",
                "0.095209"
            ],
            "rotation": [
                "0.612598",
                "0.554718",
                "0.435126",
                "0.357319"
            ]
        },
        {
            "boneName": "r_eyeout_wrinkle_bone",
            "position": [
                "-0.048838",
                "1.670483",
                "0.084694"
            ],
            "rotation": [
                "0.468482",
                "-0.223474",
                "0.820435",
                "-0.239729"
            ]
        },
        {
            "boneName": "l_eyeballaimbase_bone",
            "position": [
                "0.033045",
                "1.668441",
                "0.082970"
            ],
            "rotation": [
                "0.523415",
                "-0.493412",
                "0.475433",
                "0.506503"
            ]
        },
        {
            "boneName": "r_in_mouthdown_bone",
            "position": [
                "-0.010832",
                "1.584627",
                "0.100112"
            ],
            "rotation": [
                "0.392317",
                "-0.084412",
                "0.860928",
                "-0.312673"
            ]
        },
        {
            "boneName": "c_headaddf_bone",
            "position": [
                "0.001570",
                "1.673714",
                "-0.085371"
            ],
            "rotation": [
                "0.712842",
                "-0.165996",
                "-0.679441",
                "-0.05159"
            ]
        },
        {
            "boneName": "c_tongue1_bone",
            "position": [
                "0.001298",
                "1.590727",
                "0.032084"
            ],
            "rotation": [
                "0.493823",
                "-0.506102",
                "-0.493822",
                "0.506102"
            ]
        },
        {
            "boneName": "r_tongue2_bone",
            "position": [
                "-0.017818",
                "1.597072",
                "0.052331"
            ],
            "rotation": [
                "0.050005",
                "0.73907",
                "0.671672",
                "0.011472"
            ]
        },
        {
            "boneName": "r_eyeballaimbase_bone",
            "position": [
                "-0.031271",
                "1.668583",
                "0.085065"
            ],
            "rotation": [
                "0.49323",
                "-0.518297",
                "0.50668",
                "0.481008"
            ]
        },
        {
            "boneName": "r_nostril_bone",
            "position": [
                "-0.014545",
                "1.629134",
                "0.108535"
            ],
            "rotation": [
                "0.116306",
                "-0.236324",
                "0.962936",
                "-0.05813"
            ]
        },
        {
            "boneName": "l_down_lipsin_bone",
            "position": [
                "0.010662",
                "1.597054",
                "0.100084"
            ],
            "rotation": [
                "0.602709",
                "0.535091",
                "0.457599",
                "0.37553"
            ]
        },
        {
            "boneName": "r_cen_eyeliddownaimbase_bone",
            "position": [
                "-0.031271",
                "1.668583",
                "0.085065"
            ],
            "rotation": [
                "0.576973",
                "-0.665508",
                "0.408781",
                "0.238954"
            ]
        },
        {
            "boneName": "r_tongue3_bone",
            "position": [
                "-0.013583",
                "1.591926",
                "0.075979"
            ],
            "rotation": [
                "-0.090066",
                "0.612081",
                "0.746558",
                "-0.244736"
            ]
        },
        {
            "boneName": "l_out_forehead_bone",
            "position": [
                "0.052002",
                "1.703547",
                "0.082800"
            ],
            "rotation": [
                "0.94779",
                "0.099833",
                "0.302594",
                "-0.012794"
            ]
        },
        {
            "boneName": "l_out_mouthup_bone",
            "position": [
                "0.026290",
                "1.605030",
                "0.096812"
            ],
            "rotation": [
                "0.830825",
                "-0.054728",
                "0.54533",
                "-0.096695"
            ]
        },
        {
            "boneName": "r_upcheek_bone",
            "position": [
                "-0.011679",
                "1.560259",
                "0.088943"
            ],
            "rotation": [
                "0.386986",
                "-0.12629",
                "0.856376",
                "-0.317667"
            ]
        },
        {
            "boneName": "l_headaddside3c_bone",
            "position": [
                "0.074954",
                "1.698182",
                "-0.024348"
            ],
            "rotation": [
                "0.998092",
                "0.002462",
                "-0.044803",
                "0.042424"
            ]
        },
        {
            "boneName": "c_mouthup_bone",
            "position": [
                "-0.000236",
                "1.607805",
                "0.107899"
            ],
            "rotation": [
                "0.70686",
                "0.062112",
                "0.704618",
                "-0.001902"
            ]
        },
        {
            "boneName": "l_in_mouthup_bone",
            "position": [
                "0.012730",
                "1.608446",
                "0.105214"
            ],
            "rotation": [
                "0.859812",
                "0.129011",
                "0.493587",
                "0.021242"
            ]
        },
        {
            "boneName": "c_down_lipscenter_bone",
            "position": [
                "0.001745",
                "1.596024",
                "0.101725"
            ],
            "rotation": [
                "0.56426",
                "0.425828",
                "0.559553",
                "0.432645"
            ]
        },
        {
            "boneName": "l_center_eyebrow_bone",
            "position": [
                "0.040689",
                "1.685100",
                "0.098940"
            ],
            "rotation": [
                "0.850294",
                "-0.102268",
                "0.506608",
                "-0.099447"
            ]
        },
        {
            "boneName": "l_up_lipsin_bone",
            "position": [
                "0.010023",
                "1.596653",
                "0.099733"
            ],
            "rotation": [
                "0.567489",
                "-0.599141",
                "0.34074",
                "-0.450425"
            ]
        },
        {
            "boneName": "r_headaddside1a_bone",
            "position": [
                "-0.030797",
                "1.727367",
                "0.092895"
            ],
            "rotation": [
                "-0.511467",
                "-0.111669",
                "-0.832577",
                "-0.18096"
            ]
        },
        {
            "boneName": "l_temple_bone",
            "position": [
                "0.071104",
                "1.679327",
                "0.039516"
            ],
            "rotation": [
                "0.989856",
                "-0.027718",
                "0.137346",
                "0.023532"
            ]
        },
        {
            "boneName": "l_ear_bone",
            "position": [
                "0.073875",
                "1.652818",
                "0.003265"
            ],
            "rotation": [
                "0.987338",
                "-0.09185",
                "0.081205",
                "0.10066"
            ]
        },
        {
            "boneName": "r_masseter_bone",
            "position": [
                "-0.056453",
                "1.608118",
                "0.058825"
            ],
            "rotation": [
                "0.150236",
                "-0.035078",
                "0.982764",
                "-0.101856"
            ]
        },
        {
            "boneName": "c_noseupwrincle_bone",
            "position": [
                "0.000259",
                "1.669867",
                "0.105669"
            ],
            "rotation": [
                "0.723921",
                "-0.038258",
                "0.688609",
                "-0.01708"
            ]
        },
        {
            "boneName": "r_down_lipsin_bone",
            "position": [
                "-0.006726",
                "1.597001",
                "0.100185"
            ],
            "rotation": [
                "0.473599",
                "0.355418",
                "0.611135",
                "0.525258"
            ]
        },
        {
            "boneName": "l_in_infraorbital_bone",
            "position": [
                "0.026350",
                "1.658727",
                "0.094381"
            ],
            "rotation": [
                "-0.628922",
                "-0.020232",
                "-0.776774",
                "-0.025899"
            ]
        },
        {
            "boneName": "l_in_forehead_bone",
            "position": [
                "0.019426",
                "1.710164",
                "0.104234"
            ],
            "rotation": [
                "0.808683",
                "0.077975",
                "0.579019",
                "0.068471"
            ]
        },
        {
            "boneName": "l_headaddside1b_bone",
            "position": [
                "0.028374",
                "1.761271",
                "0.060805"
            ],
            "rotation": [
                "0.856045",
                "0.427092",
                "0.290937",
                "0.011621"
            ]
        },
        {
            "boneName": "r_merkel_bone",
            "position": [
                "-0.034018",
                "1.594677",
                "0.087456"
            ],
            "rotation": [
                "0.430519",
                "-0.04372",
                "0.894558",
                "-0.111836"
            ]
        },
        {
            "boneName": "l_out_eyelidupaimbase_bone",
            "position": [
                "0.033045",
                "1.668441",
                "0.082970"
            ],
            "rotation": [
                "-0.681312",
                "0.164197",
                "-0.189248",
                "-0.687778"
            ]
        },
        {
            "boneName": "c_submentalneck_bone",
            "position": [
                "0.001492",
                "1.550656",
                "0.062034"
            ],
            "rotation": [
                "0.533375",
                "-0.464064",
                "0.527836",
                "-0.470685"
            ]
        },
        {
            "boneName": "l_headaddside1f_bone",
            "position": [
                "0.060081",
                "1.664711",
                "-0.061282"
            ],
            "rotation": [
                "0.929583",
                "-0.031403",
                "-0.350924",
                "0.108361"
            ]
        },
        {
            "boneName": "l_up_nasolabial_bone",
            "position": [
                "0.030759",
                "1.626583",
                "0.097925"
            ],
            "rotation": [
                "0.75432",
                "-0.034355",
                "0.652389",
                "-0.064886"
            ]
        },
        {
            "boneName": "l_center_nasolabial_bone",
            "position": [
                "0.043063",
                "1.611478",
                "0.087371"
            ],
            "rotation": [
                "0.891529",
                "-0.148981",
                "0.426125",
                "-0.037398"
            ]
        },
        {
            "boneName": "l_down_nasolabial_bone",
            "position": [
                "0.045807",
                "1.583556",
                "0.069372"
            ],
            "rotation": [
                "0.942916",
                "-0.217983",
                "0.231478",
                "-0.099046"
            ]
        },
        {
            "boneName": "l_mouthdown_bone",
            "position": [
                "0.025840",
                "1.588740",
                "0.090869"
            ],
            "rotation": [
                "0.894753",
                "-0.078851",
                "0.421762",
                "0.123763"
            ]
        },
        {
            "boneName": "c_headadda_bone",
            "position": [
                "-0.001030",
                "1.735526",
                "0.096837"
            ],
            "rotation": [
                "0.676451",
                "0.191748",
                "0.683874",
                "0.194842"
            ]
        },
        {
            "boneName": "l_headaddside1c_bone",
            "position": [
                "0.025221",
                "1.777587",
                "0.016800"
            ],
            "rotation": [
                "0.832346",
                "0.549653",
                "0.06795",
                "-0.021559"
            ]
        },
        {
            "boneName": "l_out_eyeliddownaimbase_bone",
            "position": [
                "0.033045",
                "1.668441",
                "0.082970"
            ],
            "rotation": [
                "0.702583",
                "-0.323829",
                "0.07986",
                "0.628598"
            ]
        },
        {
            "boneName": "r_in_eyelidupaimbase_bone",
            "position": [
                "-0.031271",
                "1.668583",
                "0.085065"
            ],
            "rotation": [
                "0.662582",
                "-0.282209",
                "0.246952",
                "0.64835"
            ]
        },
        {
            "boneName": "l_headaddside2b_bone",
            "position": [
                "0.057871",
                "1.741796",
                "0.046938"
            ],
            "rotation": [
                "0.943749",
                "0.272519",
                "0.183354",
                "-0.038106"
            ]
        },
        {
            "boneName": "r_out_eyebrow_bone",
            "position": [
                "-0.051774",
                "1.679288",
                "0.088223"
            ],
            "rotation": [
                "0.320632",
                "-0.081069",
                "0.940831",
                "-0.073897"
            ]
        },
        {
            "boneName": "l_headaddside1d_bone",
            "position": [
                "0.056671",
                "1.755266",
                "-0.014195"
            ],
            "rotation": [
                "0.941327",
                "0.321403",
                "-0.087577",
                "0.054165"
            ]
        },
        {
            "boneName": "c_browcenter_bone",
            "position": [
                "0.000475",
                "1.681929",
                "0.108378"
            ],
            "rotation": [
                "0.701973",
                "-0.070113",
                "0.706194",
                "-0.060067"
            ]
        },
        {
            "boneName": "l_out_infraorbital_bone",
            "position": [
                "0.049034",
                "1.661645",
                "0.081216"
            ],
            "rotation": [
                "0.93073",
                "0.095134",
                "0.347902",
                "-0.06046"
            ]
        },
        {
            "boneName": "l_headaddside2c_bone",
            "position": [
                "0.072384",
                "1.728707",
                "0.009225"
            ],
            "rotation": [
                "0.985174",
                "0.128957",
                "0.033497",
                "0.108074"
            ]
        },
        {
            "boneName": "r_headaddside3a_bone",
            "position": [
                "-0.071721",
                "1.661324",
                "0.031689"
            ],
            "rotation": [
                "0.137186",
                "0.021729",
                "0.98916",
                "-0.047647"
            ]
        },
        {
            "boneName": "l_in_eyeliddownaimbase_bone",
            "position": [
                "0.033045",
                "1.668441",
                "0.082970"
            ],
            "rotation": [
                "0.443738",
                "-0.685417",
                "0.550542",
                "0.17379"
            ]
        },
        {
            "boneName": "r_temple_bone",
            "position": [
                "-0.071595",
                "1.678708",
                "0.036284"
            ],
            "rotation": [
                "0.170394",
                "0.03461",
                "0.9842",
                "-0.033441"
            ]
        },
        {
            "boneName": "l_cen_infraorbital_bone",
            "position": [
                "0.039893",
                "1.658046",
                "0.092179"
            ],
            "rotation": [
                "0.853159",
                "0.054798",
                "0.514232",
                "-0.068435"
            ]
        },
        {
            "boneName": "c_headaddc_bone",
            "position": [
                "-0.002147",
                "1.779528",
                "0.030463"
            ],
            "rotation": [
                "-0.095334",
                "0.086741",
                "-0.707313",
                "-0.695051"
            ]
        },
        {
            "boneName": "l_merkel_bone",
            "position": [
                "0.037588",
                "1.595505",
                "0.087315"
            ],
            "rotation": [
                "0.899491",
                "-0.10632",
                "0.420581",
                "-0.052198"
            ]
        },
        {
            "boneName": "c_headadde_bone",
            "position": [
                "-0.000205",
                "1.734146",
                "-0.075804"
            ],
            "rotation": [
                "0.578882",
                "-0.061939",
                "-0.701954",
                "-0.410269"
            ]
        },
        {
            "boneName": "l_cen_eyeliddownaimbase_bone",
            "position": [
                "0.033045",
                "1.668441",
                "0.082970"
            ],
            "rotation": [
                "0.6368",
                "-0.59151",
                "0.307385",
                "0.387448"
            ]
        },
        {
            "boneName": "r_angulioris_bone",
            "position": [
                "-0.029641",
                "1.583436",
                "0.085496"
            ],
            "rotation": [
                "0.422541",
                "-0.028165",
                "0.879206",
                "-0.218316"
            ]
        },
        {
            "boneName": "l_eyeout_wrinkle_bone",
            "position": [
                "0.050582",
                "1.671494",
                "0.083915"
            ],
            "rotation": [
                "0.819267",
                "-0.206043",
                "0.474746",
                "-0.246909"
            ]
        },
        {
            "boneName": "r_out_forehead_bone",
            "position": [
                "-0.052826",
                "1.702774",
                "0.083146"
            ],
            "rotation": [
                "-0.291787",
                "-0.004523",
                "-0.950903",
                "-0.103068"
            ]
        },
        {
            "boneName": "r_headaddside1d_bone",
            "position": [
                "-0.056764",
                "1.754908",
                "-0.015357"
            ],
            "rotation": [
                "0.100429",
                "-0.044248",
                "-0.944857",
                "-0.308547"
            ]
        },
        {
            "boneName": "r_down_lipsout_bone",
            "position": [
                "-0.014075",
                "1.597035",
                "0.095584"
            ],
            "rotation": [
                "0.387778",
                "0.415308",
                "0.629983",
                "0.529405"
            ]
        },
        {
            "boneName": "r_headaddside1b_bone",
            "position": [
                "-0.029569",
                "1.760435",
                "0.059983"
            ],
            "rotation": [
                "-0.296082",
                "-0.013754",
                "-0.85584",
                "-0.423893"
            ]
        },
        {
            "boneName": "r_in_mouthup_bone",
            "position": [
                "-0.011638",
                "1.609243",
                "0.104609"
            ],
            "rotation": [
                "-0.479176",
                "-0.017336",
                "-0.868545",
                "-0.125378"
            ]
        },
        {
            "boneName": "l_masseter_bone",
            "position": [
                "0.059109",
                "1.609332",
                "0.057965"
            ],
            "rotation": [
                "0.985996",
                "-0.095475",
                "0.131364",
                "-0.037956"
            ]
        },
        {
            "boneName": "r_headaddside2b_bone",
            "position": [
                "-0.058451",
                "1.740686",
                "0.045551"
            ],
            "rotation": [
                "-0.164263",
                "0.033404",
                "-0.957172",
                "-0.236058"
            ]
        },
        {
            "boneName": "r_headaddzygoma_bone",
            "position": [
                "-0.052779",
                "1.645164",
                "0.080817"
            ],
            "rotation": [
                "-0.376728",
                "0.016023",
                "-0.924643",
                "-0.053433"
            ]
        },
        {
            "boneName": "l_headaddside3b_bone",
            "position": [
                "0.071928",
                "1.682044",
                "0.006247"
            ],
            "rotation": [
                "0.990453",
                "-0.119646",
                "-0.017131",
                "-0.066284"
            ]
        },
        {
            "boneName": "r_down_mouthcorner_bone",
            "position": [
                "-0.019437",
                "1.596879",
                "0.090951"
            ],
            "rotation": [
                "0.566787",
                "0.576909",
                "0.45251",
                "0.375717"
            ]
        },
        {
            "boneName": "r_center_nasolabial_bone",
            "position": [
                "-0.040843",
                "1.610631",
                "0.087514"
            ],
            "rotation": [
                "0.415025",
                "-0.031942",
                "0.897796",
                "-0.143863"
            ]
        },
        {
            "boneName": "r_mouthdown_bone",
            "position": [
                "-0.021859",
                "1.587901",
                "0.091492"
            ],
            "rotation": [
                "0.419723",
                "0.114075",
                "0.896149",
                "-0.087956"
            ]
        },
        {
            "boneName": "l_up_lipsout_bone",
            "position": [
                "0.017243",
                "1.596841",
                "0.095452"
            ],
            "rotation": [
                "0.586763",
                "-0.655688",
                "0.325043",
                "-0.346597"
            ]
        },
        {
            "boneName": "r_headaddside2c_bone",
            "position": [
                "-0.072306",
                "1.727409",
                "0.007609"
            ],
            "rotation": [
                "-0.016593",
                "-0.088322",
                "-0.987904",
                "-0.126372"
            ]
        },
        {
            "boneName": "r_out_mouthup_bone",
            "position": [
                "-0.024051",
                "1.604774",
                "0.096642"
            ],
            "rotation": [
                "-0.479194",
                "0.051351",
                "-0.876206",
                "-0.00054"
            ]
        },
        {
            "boneName": "c_tongue4_bone",
            "position": [
                "0.001300",
                "1.593775",
                "0.091158"
            ],
            "rotation": [
                "0.678526",
                "0.199003",
                "0.678526",
                "0.199003"
            ]
        },
        {
            "boneName": "l_in_eyebrow_bone",
            "position": [
                "0.020098",
                "1.682390",
                "0.105739"
            ],
            "rotation": [
                "0.783851",
                "-0.190056",
                "0.577532",
                "-0.12615"
            ]
        },
        {
            "boneName": "l_nostril_bone",
            "position": [
                "0.014265",
                "1.628384",
                "0.109277"
            ],
            "rotation": [
                "0.951529",
                "-0.035321",
                "0.215507",
                "-0.216569"
            ]
        },
        {
            "boneName": "r_ear_bone",
            "position": [
                "-0.073132",
                "1.648674",
                "0.002687"
            ],
            "rotation": [
                "0.081715",
                "0.100596",
                "0.987298",
                "-0.0919"
            ]
        },
        {
            "boneName": "r_headaddside2a_bone",
            "position": [
                "-0.063387",
                "1.699648",
                "0.062260"
            ],
            "rotation": [
                "-0.183764",
                "0.026604",
                "-0.982342",
                "-0.022982"
            ]
        },
        {
            "boneName": "l_out_eyebrow_bone",
            "position": [
                "0.052990",
                "1.680128",
                "0.087130"
            ],
            "rotation": [
                "0.944993",
                "-0.054496",
                "0.311856",
                "-0.08225"
            ]
        },
        {
            "boneName": "jawaimbase_bone",
            "position": [
                "0.000717",
                "1.614309",
                "0.006496"
            ],
            "rotation": [
                "0.579036",
                "-0.576267",
                "0.405853",
                "0.409776"
            ]
        },
        {
            "boneName": "r_up_mouthcorner_bone",
            "position": [
                "-0.020014",
                "1.596759",
                "0.091515"
            ],
            "rotation": [
                "0.386856",
                "-0.574416",
                "0.442148",
                "-0.569994"
            ]
        },
        {
            "boneName": "l_cen_eyelidupaimbase_bone",
            "position": [
                "0.033045",
                "1.668441",
                "0.082970"
            ],
            "rotation": [
                "-0.487706",
                "0.353438",
                "-0.511999",
                "-0.612439"
            ]
        },
        {
            "boneName": "l_infraorbitalfurrow_bone",
            "position": [
                "0.055309",
                "1.629772",
                "0.078985"
            ],
            "rotation": [
                "0.957809",
                "-0.054925",
                "0.277614",
                "-0.050161"
            ]
        },
        {
            "boneName": "r_cen_infraorbital_bone",
            "position": [
                "-0.039044",
                "1.657823",
                "0.093356"
            ],
            "rotation": [
                "0.487401",
                "-0.070226",
                "0.870134",
                "-0.0194"
            ]
        },
        {
            "boneName": "l_headaddbangs_bone",
            "position": [
                "0.049582",
                "1.690017",
                "0.090205"
            ],
            "rotation": [
                "0.952616",
                "0.11267",
                "0.282493",
                "0.005168"
            ]
        },
        {
            "boneName": "r_headaddside1g_bone",
            "position": [
                "-0.048660",
                "1.617760",
                "-0.038645"
            ],
            "rotation": [
                "-0.283314",
                "0.110496",
                "0.946274",
                "-0.109952"
            ]
        },
        {
            "boneName": "r_headaddside1c_bone",
            "position": [
                "-0.026397",
                "1.777059",
                "0.016227"
            ],
            "rotation": [
                "-0.06393",
                "0.026137",
                "-0.839713",
                "-0.538621"
            ]
        },
        {
            "boneName": "l_headaddside1a_bone",
            "position": [
                "0.030206",
                "1.727246",
                "0.092863"
            ],
            "rotation": [
                "0.845691",
                "0.181326",
                "0.491164",
                "0.103371"
            ]
        },
        {
            "boneName": "r_up_lipsin_bone",
            "position": [
                "-0.007832",
                "1.596542",
                "0.100479"
            ],
            "rotation": [
                "0.371326",
                "-0.463304",
                "0.571921",
                "-0.566015"
            ]
        },
        {
            "boneName": "r_out_eyelidupaimbase_bone",
            "position": [
                "-0.031271",
                "1.668583",
                "0.085065"
            ],
            "rotation": [
                "-0.14553",
                "0.686636",
                "-0.691969",
                "-0.168912"
            ]
        },
        {
            "boneName": "c_headaddb_bone",
            "position": [
                "-0.001755",
                "1.756086",
                "0.079348"
            ],
            "rotation": [
                "0.636543",
                "0.288262",
                "0.654242",
                "0.289285"
            ]
        },
        {
            "boneName": "c_tonguetop_bone",
            "position": [
                "0.001300",
                "1.606006",
                "0.053069"
            ],
            "rotation": [
                "0.520878",
                "0.478211",
                "0.520878",
                "0.478211"
            ]
        },
        {
            "boneName": "r_cen_eyelidupaimbase_bone",
            "position": [
                "-0.031271",
                "1.668583",
                "0.085065"
            ],
            "rotation": [
                "-0.368302",
                "0.47648",
                "-0.603617",
                "-0.522463"
            ]
        },
        {
            "boneName": "l_infraorbitalfurrowup_bone",
            "position": [
                "0.048390",
                "1.644975",
                "0.086914"
            ],
            "rotation": [
                "0.879574",
                "0.124718",
                "0.457948",
                "0.032847"
            ]
        },
        {
            "boneName": "l_cheek_bone",
            "position": [
                "0.061488",
                "1.608015",
                "0.021402"
            ],
            "rotation": [
                "0.984883",
                "-0.159982",
                "-0.052468",
                "0.040725"
            ]
        },
        {
            "boneName": "r_infraorbitalfurrowup_bone",
            "position": [
                "-0.046901",
                "1.644472",
                "0.085699"
            ],
            "rotation": [
                "-0.459365",
                "-0.032685",
                "-0.884195",
                "-0.078191"
            ]
        },
        {
            "boneName": "r_headaddside1e_bone",
            "position": [
                "-0.060878",
                "1.720262",
                "-0.047747"
            ],
            "rotation": [
                "0.267436",
                "-0.042956",
                "-0.955105",
                "-0.120031"
            ]
        },
        {
            "boneName": "r_up_lipsout_bone",
            "position": [
                "-0.014757",
                "1.595990",
                "0.096819"
            ],
            "rotation": [
                "0.362674",
                "-0.314589",
                "0.578344",
                "-0.65956"
            ]
        },
        {
            "boneName": "c_headaddd_bone",
            "position": [
                "-0.001415",
                "1.771547",
                "-0.039040"
            ],
            "rotation": [
                "0.252449",
                "-0.139513",
                "-0.694145",
                "-0.659522"
            ]
        },
        {
            "boneName": "l_headaddside3a_bone",
            "position": [
                "0.071183",
                "1.662085",
                "0.034448"
            ],
            "rotation": [
                "0.996809",
                "-0.021425",
                "0.076889",
                "0.000242"
            ]
        },
        {
            "boneName": "l_up_mouthcorner_bone",
            "position": [
                "0.023351",
                "1.597767",
                "0.089998"
            ],
            "rotation": [
                "0.464732",
                "-0.555585",
                "0.440907",
                "-0.530048"
            ]
        },
        {
            "boneName": "r_cheek_bone",
            "position": [
                "-0.058527",
                "1.606692",
                "0.023630"
            ],
            "rotation": [
                "-0.079842",
                "0.020359",
                "0.978915",
                "-0.186911"
            ]
        },
        {
            "boneName": "r_headaddside3b_bone",
            "position": [
                "-0.075086",
                "1.680915",
                "0.001537"
            ],
            "rotation": [
                "-0.102894",
                "-0.013155",
                "0.994261",
                "-0.026161"
            ]
        },
        {
            "boneName": "r_in_forehead_bone",
            "position": [
                "-0.018585",
                "1.710467",
                "0.104350"
            ],
            "rotation": [
                "-0.595204",
                "-0.073243",
                "-0.795458",
                "-0.087262"
            ]
        },
        {
            "boneName": "r_nose_nasolabial_bone",
            "position": [
                "-0.021778",
                "1.641036",
                "0.097851"
            ],
            "rotation": [
                "-0.541436",
                "-0.039189",
                "-0.825849",
                "-0.152596"
            ]
        },
        {
            "boneName": "r_headaddside3d_bone",
            "position": [
                "-0.067433",
                "1.650388",
                "-0.022945"
            ],
            "rotation": [
                "-0.191178",
                "0.116819",
                "0.967168",
                "-0.119961"
            ]
        }
    ]
}